Workbook

Sheet Read Me
A1: Chase-Lift Soaring Register
A2: Compiled 2026-09-22 for Martin (GBSC). Rates, policies and fleets are as published by each operator on that date; anything marked 'unverified' or 'call' needs a phone call before a trip.
A4: Sheets
A5: Operators: one row per site. Rank = ease of short-notice rental for a visiting licensed pilot (1 = easiest) within its region; 0 = not ranked.
A6: Rental Procedures: what it takes to rent, costs, tall-pilot notes, sources.
A7: Fleet Register: every glider found, with N-number where the FAA registry or fleet page gave one; performance columns pull from Glider Types.
A8: Glider Types: glide ratio, speeds, span and cockpit notes per type.
A9: Travel: flight tiers from Boston on a Friday evening.
A10: Contact Log: fill this in as you build relationships (one row per call/email/visit).
A12: Rental categories
A13: RENT: Rents to visitors
A14: GUEST: Guest / short-term membership
... A29: Tall-pilot rule: sit in the actual glider before planning a trip around it. Tall-pilot notes are general type reputation unless the operator stated a limit.

Sheet Operators
A1: ID | B1: Operator | C1: Type | D1: Region | E1: Airport | F1: Town | G1: Access | H1: Travel from Newton | I1: Soaring | J1: Season / days | K1: Rental status | L1: Rank | M1: Gliders listed | N1: Phone | O1: Email | P1: Contacts | Q1: Website | R1: Lat | S1: Lon | T1: Last verified
A2: SUGAR | B2: Sugarbush Soaring | C2: Commercial-style club | D2: New England | E2: Warren-Sugarbush (0B7) | F2: Warren, VT | G2: Van, about 4 h | H2: 191 mi; 3:15 typical, 3:45-4:00 Fri | I2: Thermal, ridge, wave | J2: 7 days (closed Tue), roughly May-Oct; airport closed Nov-Apr | K2: Rents to visitors | L2: 1 | M2: =COUNTIF('Fleet Register'!$A:$A,A2) -> 5 | N2: 802-496-2290 | O2: (via website) | P2: Not published | Q2: https://sugarbushsoaring.com/ | R2: 44.1174 | S2: -72.827 | T2: 2026-09-22
A3: GBSC | B3: Greater Boston Soaring Club (home club) | C3: Club | D3: New England | E3: Sterling (3B3) | F3: Sterling, MA | G3: Van, 4 h or less | H3: 45 mi; 0:50 typical, 1:15-1:30 Fri evening | I3: Thermal | J3: Weekends + holidays, Apr-Nov; some weekdays | K3: Membership required | L3: 2 | M3: =COUNTIF('Fleet Register'!$A:$A,A3) -> 8 | N3: (field phone not published) | O3: membership@soargbsc.com | P3: Tony Verhulst (groups.io); Dwight Schirmer (treasurer); Ken Flaton (evening ground school) | Q3: https://www.soargbsc.net/ | R3: 42.4259 | S3: -71.7929 | T3: 2026-09-22
A4: MOHAWK | B4: Mohawk Soaring Club | C4: Club | D4: New England | E4: Harriman-and-West (AQW) | F4: North Adams, MA | G4: Van, 4 h or less | H4: ~135 mi; 2:40 typical, 3:10 Fri | I4: Ridge (Mt Greylock, Taconics), thermal | J4: Saturdays + one midweek day (usually Wed), Apr-Nov | K4: Guest / short-term membership | L4: 3 | M4: =COUNTIF('Fleet Register'!$A:$A,A4) -> 6 | N4: (not published) | O4: doug.herrick at rcn.com (rides) | P4: Doug Herrick (rides); Jon Goodman (president, 2022) | Q4: http://www.soarmohawk.com/ | R4: 42.6963 | S4: -73.1706 | T4: 2026-09-22
A5: POSTMILLS | B5: Post Mills Soaring Club | C5: Club | D5: New England | E5: Post Mills (2B9) | F5: Post Mills, VT | G5: Van, 4 h or less | H5: 155 mi; 2:40 typical, 3:10 Fri | I5: Thermal | J5: Weekends assumed (unverified), spring-fall | K5: Membership required | L5: 4 | M5: =COUNTIF('Fleet Register'!$A:$A,A5) -> 4 | N5: 802-333-9401 | O5: andrew.e.lumley@gmail.com | P5: Andy Lumley (membership + airport manager, 802-266-1355) | Q5: https://flypmsc.org/ | R5: 43.8837 | S5: -72.2521 | T5: 2026-09-22
A6: NESA | B6: New England Soaring Association | C6: Club | D6: New England | E6: Hartness State (VSF) | F6: Springfield, VT | G6: Van, 4 h or less | H6: 123 mi; 2:15 typical, 2:45 Fri | I6: Thermal | J6: Mostly weekends, Apr-Nov | K6: Membership required | L6: 5 | M6: =COUNTIF('Fleet Register'!$A:$A,A6) -> 4 | N6: (not published) | O6: (web form) | P6: Jim Malecha (pres.), Larry Perry (VP), Andy Kozak (sec.), Jerry Smith (treas.) | Q6: https://www.flynesa.com/ | R6: 43.3437 | S6: -72.5173 | T6: 2026-09-22
A7: FRANCONIA | B7: Franconia Soaring Association | C7: Club | D7: New England | E7: Franconia (1B5) | F7: Franconia, NH | G7: Van, 4 h or less | H7: 151 mi; 2:30 typical, 3:00-3:30 Fri | I7: Thermal, ridge (Cannon/Kinsman), wave | J7: Weekends + holidays, Fri by arrangement, ~May-Oct | K7: Unknown, call | L7: 6 | M7: =COUNTIF('Fleet Register'!$A:$A,A7) -> 7 | N7: 603-823-5034 | O7: franconiasoaring@gmail.com | P7: James R. David (airport manager, 603-921-1588) | Q7: http://www.franconiasoaring.org/ | R7: 44.196 | S7: -71.7507 | T7: 2026-09-22
A8: CSA | B8: Connecticut Soaring Association | C8: Club | D8: New England | E8: Windham (IJD) | F8: Windham, CT | G8: Van, 4 h or less | H8: 84 mi; 1:30 typical, 2:00 Fri | I8: Thermal | J8: ~Apr-Nov; midweek program since 2024 | K8: Membership required | L8: 7 | M8: =COUNTIF('Fleet Register'!$A:$A,A8) -> 4 | N8: 860-202-1866 | O8: contact@ctsoaring.org | P8: Not published | Q8: https://www.ctsoaring.org/ | R8: 41.744 | S8: -72.1802 | T8: 2026-09-22
A9: GORHAM | B9: Mt Washington Wave Camp (GBSC/Franconia/Post Mills) | C9: Event | D9: New England | E9: Gorham (2G8) | F9: Gorham, NH | G9: Van, about 4 h | H9: 183 mi; 3:15 typical, 3:45-4:15 Fri | I9: Wave (Mt Washington) | J9: ~10 days mid-October (Columbus Day) | K9: Membership required | M9: =COUNTIF('Fleet Register'!$A:$A,A9) -> 0 | N9: (via GBSC) | O9: (via GBSC) | P9: Run jointly by host clubs | Q9: https://www.soargbsc.com/wave/MtWashBrief.pdf | R9: 44.3931 | S9: -71.1967 | T9: 2026-09-22
A10: SANFORD | B10: Sanford Soaring | C10: Club? | D10: New England | E10: Sanford Seacoast (SFM) | F10: Sanford, ME | G10: Van, 4 h or less | H10: 92 mi; 1:40 typical, 2:15 Fri | I10: Thermal, sea breeze | J10: Unknown | K10: Closed / inactive | M10: =COUNTIF('Fleet Register'!$A:$A,A10) -> 0 | Q10: https://www.facebook.com/sanfordsoaring/ | R10: 43.3938 | S10: -70.708 | T10: 2026-09-22
A11: SPIRIT | B11: Spirit Soaring (motorglider rides) | C11: Commercial | D11: New England | E11: Knox County (RKD) | F11: Owls Head, ME | G11: Van, about 4 h | H11: 195 mi; 3:15 typical, 3:45-4:00 Fri | I11: Coastal | J11: Unknown | K11: Closed / inactive | M11: =COUNTIF('Fleet Register'!$A:$A,A11) -> 0 | P11: Dave Miramant | Q11: https://www.spiritsoaring.org/ | R11: 44.0601 | S11: -69.0997 | T11: 2026-09-22
A12: WURTS | B12: Wurtsboro Airport / Wurtsboro Flight Mgmt | C12: Commercial | D12: NY/NJ/PA | E12: Wurtsboro-Sullivan County (N82) | F12: Wurtsboro, NY | G12: Van, about 4 h | H12: 216 mi; 3:30 typical, 4:00-4:15 Fri | I12: Ridge (Shawangunk), thermal | J12: 7 days, year-round (weather) | K12: Rents to visitors | L12: 1 | M12: =COUNTIF('Fleet Register'!$A:$A,A12) -> 4 | N12: (845) 888-2791 | O12: info@wurtsboroairport.com | P12: Not published | Q12: https://www.wurtsboroairport.com/ | R12: 41.5972 | S12: -74.4583 | T12: 2026-09-22
A13: VANSANT | B13: Van Sant Airport / Bird of Paradise | C13: Commercial | D13: NY/NJ/PA | E13: Van Sant (9N1) | F13: Erwinna, PA | G13: Fly Friday night | H13: PHL + 1:15 (drive 5:00+) | I13: Thermal, some ridge | J13: Tue-Sun 9-4, year-round | K13: Rents to visitors | L13: 2 | M13: =COUNTIF('Fleet Register'!$A:$A,A13) -> 2 | N13: (610) 847-1119 | P13: Office (610) 847-8494 | Q13: https://vansantairport.com/ | R13: 40.4842 | S13: -75.0997 | T13: 2026-09-22
A14: HHSC | B14: Harris Hill Soaring Corp | C14: Club | D14: NY/NJ/PA | E14: Harris Hill Gliderport (4NY8) | F14: Elmira, NY | G14: Fly Friday night | H14: 5:30 drive; or SYR + 1:45 / BUF + 2:30 | I14: Ridge, thermal | J14: ~Apr-Oct; weekends (daily Jun-mid Aug) | K14: Guest / short-term membership | L14: 3 | M14: =COUNTIF('Fleet Register'!$A:$A,A14) -> 7 | N14: (607) 734-0641 | O14: newmember@ / training@harrishillsoaring.org | Q14: https://harrishillsoaring.org/ | R14: 42.1209 | S14: -76.9011 | T14: 2026-09-22
A15: PSA | B15: Pittsburgh Soaring Association | C15: Club | D15: NY/NJ/PA | E15: Greene County (WAY) | F15: Waynesburg, PA | G15: Fly Friday night | H15: PIT + ~1:00 | I15: Thermal | J15: Weekends | K15: Guest / short-term membership | L15: 4 | M15: =COUNTIF('Fleet Register'!$A:$A,A15) -> 3 | Q15: http://pghsoar.org/ | R15: 39.9 | S15: -80.133 | T15: 2026-09-22
A16: ASA | B16: Adirondack Soaring Association | C16: Club | D16: NY/NJ/PA | E16: Saratoga County (5B2) | F16: Ballston Spa, NY | G16: Van, 4 h or less | H16: 193 mi; 3:15 typical, 3:45 Fri | I16: Thermal, some ridge | J16: Every weekend + some weekdays, Apr-Nov | K16: Guest / short-term membership | L16: 5 | M16: =COUNTIF('Fleet Register'!$A:$A,A16) -> 4 | N16: (518) 693-6849 | O16: (web) | P16: Eric Davenport (pres.); Tim Hanke (dir. of ops) | Q16: https://www.adirondacksoaring.com/ | R16: 43.0512 | S16: -73.8612 | T16: 2026-09-22
A17: ACA | B17: Aero Club Albatross | C17: Club | D17: NY/NJ/PA | E17: Blairstown (1N7) + Wurtsboro (N82) | F17: Blairstown, NJ | G17: Out of range | H17: 266 mi to Blairstown; 4:45-5:00 Fri (Wurtsboro ~4:00) | I17: Ridge (Kittatinny, Shawangunk), thermal | J17: Wurtsboro 7 days; Blairstown weekends | K17: Membership required | L17: 6 | M17: =COUNTIF('Fleet Register'!$A:$A,A17) -> 8 | N17: (973) 294-5146 | O17: AeroClubAlbatross@gmail.com | P17: Not published | Q17: https://www.aeroclubalbatross.org/ | R17: 40.9712 | S17: -74.9975 | T17: 2026-09-22
A18: FLSC | B18: Finger Lakes Soaring Club | C18: Club | D18: NY/NJ/PA | E18: Dansville (DSV) | F18: Dansville, NY | G18: Fly Friday night | H18: BUF/ROC + ~1:00 | I18: Thermal | J18: Weekends 9-5, Apr-Nov | K18: Guest / short-term membership | L18: 7 | M18: =COUNTIF('Fleet Register'!$A:$A,A18) -> 5 | N18: (585) 335-5849 | O18: contact@flsc.org | P18: Rick Lafford (airport mgr, 585-444-3612) | Q18: https://flsc.org/ | R18: 42.571 | S18: -77.713 | T18: 2026-09-22
A19: JRS | B19: Jersey Ridge Soaring | C19: Commercial | D19: NY/NJ/PA | E19: Blairstown (1N7) | F19: Blairstown, NJ | G19: Out of range | H19: 266 mi; 4:15 typical, 4:45-5:00 Fri; or PHL + 1:45 | I19: Ridge (Kittatinny), thermal | J19: Weekends, year-round; tows 7 days | K19: Unknown, call | L19: 8 | M19: =COUNTIF('Fleet Register'!$A:$A,A19) -> 4 | N19: (908) 362-1239 | O19: info@jerseyridgesoaring.com | P19: Kevin & Brenda Martin (owners); Michael Friedman (chief instructor) | Q19: https://www.jerseyridgesoaring.com/ | R19: 40.973 | S19: -74.995 | T19: 2026-09-22
A20: BSA | B20: Brandywine Soaring Association | C20: Club | D20: NY/NJ/PA | E20: New Garden (N57) | F20: Toughkenamon, PA | G20: Fly Friday night | H20: PHL + ~1:00 | I20: Thermal | J20: Wed + weekends, May-Oct | K20: Guest / short-term membership | L20: 9 | M20: =COUNTIF('Fleet Register'!$A:$A,A20) -> 4 | O20: membership@brandywinesoaring.org | Q20: https://www.brandywinesoaring.org/ | R20: 39.831 | S20: -75.77 | T20: 2026-09-22
A21: VSC | B21: Valley Soaring Club | C21: Club | D21: NY/NJ/PA | E21: Randall (06N) | F21: Middletown, NY | G21: Van, about 4 h | H21: ~3:30 typical, ~4:00 Fri | I21: Thermal | J21: Weekends + Mon holidays, Apr-Dec | K21: Unknown, call | L21: 10 | M21: =COUNTIF('Fleet Register'!$A:$A,A21) -> 4 | N21: (845) 564-2054 | Q21: (login-only site) | R21: 41.4319 | S21: -74.3916 | T21: 2026-09-22
A22: PGC | B22: Philadelphia Glider Council | C22: Club | D22: NY/NJ/PA | E22: Philadelphia Gliderport (3PA2) | F22: Hilltown, PA | G22: Fly Friday night | H22: PHL + ~1:00 | I22: Thermal | J22: Weekends | K22: Membership required | L22: 11 | M22: =COUNTIF('Fleet Register'!$A:$A,A22) -> 4 | N22: 215-334-5980 | Q22: https://pgcsoaring.org/ | R22: 40.3312 | S22: -75.2481 | T22: 2026-09-22
A23: TIGERS | B23: Soaring Tigers | C23: Club | D23: NY/NJ/PA | E23: Van Sant (9N1) | F23: Erwinna, PA | G23: Fly Friday night | H23: PHL + 1:15 | I23: Thermal | J23: Wed-Sun | K23: Membership required | L23: 13 | M23: =COUNTIF('Fleet Register'!$A:$A,A23) -> 3 | N23: (610) 847-1119 | Q23: https://soaringtigers.org/ | R23: 40.486 | S23: -75.0975 | T23: 2026-09-22
A24: LISA | B24: Long Island Soaring Association | C24: Club | D24: NY/NJ/PA | E24: Brookhaven Calabro (HWV) | F24: Shirley, NY | G24: Out of range | H24: 4+ h | I24: Thermal (flat coastal) | J24: Weekends, some Wed | K24: Membership required | L24: 14 | M24: =COUNTIF('Fleet Register'!$A:$A,A24) -> 3 | N24: 631-578-8596 | Q24: https://longislandsoaring.com/ | R24: 40.822 | S24: -72.869 | T24: 2026-09-22
A25: SKYLINE | B25: Skyline Soaring Club | C25: Club | D25: Mid-Atlantic | E25: Front Royal (FRR); at Petersburg WV (W99) from 16 Sep 2026 | F25: Front Royal, VA | G25: Fly Friday night | H25: IAD + ~1:00 (Petersburg ~2:45) | I25: Thermal, ridge; wave at Petersburg | J25: Weekends + some weekdays | K25: Guest / short-term membership | L25: 2 | M25: =COUNTIF('Fleet Register'!$A:$A,A25) -> 3 | O25: welcome@skylinesoaring.org | Q25: https://www.skylinesoaring.org/ | R25: 38.9175 | S25: -78.2535 | T25: 2026-09-22
A26: BRSS | B26: Blue Ridge Soaring Society | C26: Club | D26: Mid-Atlantic | E26: New Castle (VA85) | F26: New Castle, VA | G26: Fly Friday night | H26: IAD/CLT/RDU + 3:30-4:00 | I26: Ridge, wave (to 23,000 ft), thermal | J26: Weekends | K26: Guest / short-term membership | L26: 5 | M26: =COUNTIF('Fleet Register'!$A:$A,A26) -> 2 | N26: 540-864-5800 (airport owner) | O26: (web form) | P26: Lanier Frantz (airport owner) | Q26: https://www.brss.net/ | R26: 37.4835 | S26: -80.0998 | T26: 2026-09-22
A27: SVS | B27: Shenandoah Valley Soaring | C27: Club | D27: Mid-Atlantic | E27: Rockfish Gliderport (VG22) | F27: Nellysford, VA | G27: Fly Friday night | H27: IAD/DCA + ~2:45-3:00 | I27: Thermal, ridge | J27: Weekends, year-round | K27: Guest / short-term membership | L27: 6 | M27: =COUNTIF('Fleet Register'!$A:$A,A27) -> 2 | O27: (web form) | Q27: https://www.svsoar.org/ | R27: 37.8788 | S27: -78.8935 | T27: 2026-09-22
A28: MASA | B28: Mid-Atlantic Soaring Association | C28: Club | D28: Mid-Atlantic | E28: Fairfield (W73) | F28: Fairfield, PA | G28: Fly Friday night | H28: BWI/IAD + ~1:30 | I28: Thermal, ridge, wave | J28: Mar-Nov | K28: Membership required | L28: 12 | M28: =COUNTIF('Fleet Register'!$A:$A,A28) -> 5 | N28: 717-642-9907 (airport) | O28: joinus@midatlanticsoaring.org | P28: Mark Philip (airport mgr) | Q28: https://midatlanticsoaring.org/ | R28: 39.757 | S28: -77.3514 | T28: 2026-09-22
A29: ESC | B29: Eastern Soaring Center | C29: Commercial | D29: Mid-Atlantic | E29: Grant County (W99) | F29: Petersburg, WV | G29: Fly Friday night | H29: IAD + ~2:45 | I29: Thermal, ridge, wave (FL230 window) | J29: Closed for 2026 | K29: Closed / inactive | M29: =COUNTIF('Fleet Register'!$A:$A,A29) -> 1 | N29: 304-851-4106 | O29: gliding@EasternSoaringCenter.com | P29: Brian Collins (owner, DPE) | Q29: https://www.easternsoaringcenter.com/ | R29: 38.9914 | S29: -79.1456 | T29: 2026-09-22
A30: TSS | B30: Tidewater Soaring Society | C30: Club | D30: Mid-Atlantic | E30: Garner (3VA8) | F30: Windsor, VA | G30: Fly Friday night | H30: RDU + 2:45 | I30: Thermal | J30: Weekends, year-round | K30: Membership required | M30: =COUNTIF('Fleet Register'!$A:$A,A30) -> 0 | N30: 757-377-6174 (landing permission) | P30: W.E. Laine Jr. | Q30: https://tss.fyi/ | R30: 36.8563 | S30: -76.6822 | T30: 2026-09-22
A31: CHIL | B31: Chilhowee Gliderport | C31: Commercial | D31: Southeast | E31: Chilhowee (92A) | F31: Benton, TN | G31: Fly Friday night | H31: ATL + 2:15; BNA + 3:00 | I31: Thermal (spring-fall), ridge (fall-spring), occasional wave | J31: Fri-Sun 11:00-sunset, year-round | K31: Rents to visitors | L31: 1 | M31: =COUNTIF('Fleet Register'!$A:$A,A31) -> 5 | N31: 423-338-2000 (cell 423-506-9015) | O31: info@chilhowee.com | P31: Sarah Arnold (bookings) | Q31: https://www.chilhowee.com/ | R31: 35.2265 | S31: -84.5849 | T31: 2026-09-22
A32: BHS | B32: Bermuda High Soaring | C32: Commercial + club | D32: Southeast | E32: Bermuda High Gliderport (SC79) | F32: Jefferson, SC | G32: Fly Friday night | H32: CLT + 1:15 | I32: Thermal | J32: Weekends 10-5, year-round | K32: Unknown, call | L32: 4 | M32: =COUNTIF('Fleet Register'!$A:$A,A32) -> 3 | N32: (803) 475-7627 | P32: Jayne Ewing Reid; Frank Reid | Q32: https://bermudahighsoaring.com/ | R32: 34.6113 | S32: -80.4498 | T32: 2026-09-22
A33: CAROLINA | B33: Carolina Soaring Association | C33: Club | D33: Southeast | E33: Spartanburg Downtown (SPA) | F33: Spartanburg, SC | G33: Fly Friday night | H33: CLT + 1:15 | I33: Thermal | J33: Weekends | K33: Membership required | M33: =COUNTIF('Fleet Register'!$A:$A,A33) -> 2 | N33: 864-256-1741 | Q33: https://carolinasoaring.org/ | R33: 34.9157 | S33: -81.9565 | T33: 2026-09-22
A34: NCSA | B34: North Carolina Soaring Association | C34: Club | D34: Southeast | E34: Crooked Creek (7NC5) | F34: Bunn, NC | G34: Fly Friday night | H34: RDU + 0:45 | I34: Thermal | J34: Every weekend day | K34: Membership required | M34: =COUNTIF('Fleet Register'!$A:$A,A34) -> 0 | N34: 919-215-1356 (field owner) | O34: info@soaringnc.org | P34: Frank Swett | Q34: https://soaringnc.org/ | R34: 35.9312 | S34: -78.2448 | T34: 2026-09-22
A35: MGSA | B35: Mid-Georgia Soaring Association | C35: Club | D35: Southeast | E35: Monroe (D73) | F35: Monroe, GA | G35: Fly Friday night | H35: ATL + 1:00 | I35: Thermal | J35: Most weekends | K35: Membership required | M35: =COUNTIF('Fleet Register'!$A:$A,A35) -> 3 | O35: membershipinfo@soar-mgsa.org | Q35: https://www.soar-mgsa.org/ | R35: 33.7823 | S35: -83.6926 | T35: 2026-09-22
A36: EAGLEVILLE | B36: Eagleville Soaring Club | C36: Club | D36: Southeast | E36: Puckett Gliderport (50M) | F36: Eagleville, TN | G36: Fly Friday night | H36: BNA + 0:45 | I36: Thermal | J36: Most weekends, year-round | K36: Membership required | M36: =COUNTIF('Fleet Register'!$A:$A,A36) -> 3 | N36: 800-306-6690 | O36: info@eaglevillesoaring.org | Q36: https://eaglevillesoaring.org/ | R36: 35.6894 | S36: -86.615 | T36: 2026-09-22
A37: SANDHILL | B37: Sandhill Soaring Club | C37: Club | D37: Midwest | E37: Richmond Field (69G) | F37: Gregory, MI | G37: Fly Friday night | H37: DTW + 1:00 | I37: Thermal | J37: Weekends Apr-Nov + weekdays | K37: Guest / short-term membership | L37: 3 | M37: =COUNTIF('Fleet Register'!$A:$A,A37) -> 5 | N37: 734-498-2075 (field mgr) | P37: Michael Campbell (field mgr) | Q37: https://www.sandhillsoaring.org/ | R37: 42.442 | S37: -84.0643 | T37: 2026-09-22
A38: SKYSOAR | B38: Sky Soaring | C38: Club | D38: Midwest | E38: Sky Soaring (55LL) | F38: Hampshire, IL | G38: Fly Friday night | H38: ORD + 0:50 | I38: Thermal | J38: Mid-Apr-Oct | K38: Membership required | M38: =COUNTIF('Fleet Register'!$A:$A,A38) -> 4 | N38: (847) 683-7627 | Q38: https://skysoaring.com/ | R38: 42.1542 | S38: -88.5115 | T38: 2026-09-22
A39: CGC | B39: Chicago Glider Club | C39: Club | D39: Midwest | E39: Chicago Glider Club (IL59) | F39: Minooka, IL | G39: Fly Friday night | H39: MDW + 0:50 | I39: Thermal | J39: Apr-Oct | K39: Membership required | M39: =COUNTIF('Fleet Register'!$A:$A,A39) -> 3 | N39: 630-854-9456 | P39: Ron Ridenour (manager) | Q39: http://www.chicagogliderclub.org/ | R39: 41.432 | S39: -88.2473 | T39: 2026-09-22
A40: CCSC | B40: Caesar Creek Soaring Club | C40: Club | D40: Midwest | E40: Caesar Creek Gliderport (2OH9) | F40: Waynesville, OH | G40: Fly Friday night | H40: CMH + 1:15 | I40: Thermal | J40: Weekends + Wed, year-round | K40: Membership required | M40: =COUNTIF('Fleet Register'!$A:$A,A40) -> 4 | N40: 513-932-7627 | O40: ccsc@soarccsc.com | Q40: https://www.soarccsc.com/ | R40: 39.4767 | S40: -84.0938 | T40: 2026-09-22
A41: SEMINOLE | B41: Seminole-Lake Gliderport | C41: Commercial | D41: Florida | E41: Seminole Lake Gliderport (6FL0) | F41: Clermont, FL | G41: Fly Friday night | H41: MCO + 0:45 | I41: Thermal, sea-breeze convergence; best Mar-May | J41: Tue-Sun (winter), Wed-Sun (summer) | K41: Rents to visitors | L41: 1 | M41: =COUNTIF('Fleet Register'!$A:$A,A41) -> 2 | N41: 352-394-5450 | O41: office@soarfl.com | Q41: https://www.soarfl.com/ | R41: 28.4058 | S41: -81.8379 | T41: 2026-09-22
A42: MIAMI | B42: Miami Gliders | C42: Commercial | D42: Florida | E42: Homestead General (X51) | F42: Homestead, FL | G42: Fly Friday night | H42: MIA + 0:50; FLL + 1:15 | I42: Thermal | J42: Call | K42: Rents to visitors | L42: 3 | M42: =COUNTIF('Fleet Register'!$A:$A,A42) -> 3 | N42: (786) 243-7640 | O42: fly@miamigliders.com | Q42: https://www.miamigliders.com/ | R42: 25.4988 | S42: -80.5543 | T42: 2026-09-22
A43: TBSS | B43: Tampa Bay Soaring Society | C43: Club | D43: Florida | E43: Zephyrhills (ZPH) | F43: Zephyrhills, FL | G43: Fly Friday night | H43: TPA + 0:45 | I43: Thermal | J43: Wed, Sat, Sun, year-round | K43: Membership required | L43: 11 | M43: =COUNTIF('Fleet Register'!$A:$A,A43) -> 5 | N43: 813-780-0031 | Q43: https://www.tampabaysoaring.com/ | R43: 28.2267 | S43: -82.1556 | T43: 2026-09-22
A44: TSA | B44: Texas Soaring Association | C44: Club | D44: Texas | E44: TSA Gliderport (TA11) | F44: Midlothian, TX | G44: Fly Friday night | H44: DFW + 0:50 (Tier C fares) | I44: Thermal; best Apr-Sep | J44: Thu, Sat, Sun, year-round | K44: Guest / short-term membership | L44: 5 | M44: =COUNTIF('Fleet Register'!$A:$A,A44) -> 4 | N44: 972-775-4234 | O44: (web) | P44: Marco (membership director) | Q44: https://texassoaring.org/ | R44: 32.3835 | S44: -97.0142 | T44: 2026-09-22
A45: SCH | B45: Soaring Club of Houston | C45: Club | D45: Texas | E45: SCH Gliderport (89TA) | F45: Waller, TX | G45: Fly Friday night | H45: IAH + 1:00 | I45: Thermal | J45: Sat-Sun | K45: Guest / short-term membership | L45: 6 | M45: =COUNTIF('Fleet Register'!$A:$A,A45) -> 3 | Q45: https://sites.google.com/site/soaringclubofhouston/ | R45: 30.1927 | S45: -95.9633 | T45: 2026-09-22
A46: FLF | B46: Fault Line Flyers | C46: Club | D46: Texas | E46: FLF field (private) | F46: Briggs/Bertram, TX | G46: Fly Friday night | H46: AUS + 1:15 | I46: Thermal | J46: Every weekend | K46: Guest / short-term membership | L46: 8 | M46: =COUNTIF('Fleet Register'!$A:$A,A46) -> 4 | N46: (512) 489-0460 | O46: soar.flf@gmail.com | P46: Bins Ely (president) | Q46: https://www.faultlineflyers.com/ | R46: 30.88 | S46: -97.93 | T46: 2026-09-22
A47: MHG | B47: Mile High Gliding | C47: Commercial | D47: Mountain West | E47: Boulder Municipal (BDU) | F47: Boulder, CO | G47: Fly Friday night | H47: DEN + 0:45 | I47: Mountain thermal; wave Nov-Mar | J47: Wed-Sun year-round | K47: Rents to visitors | L47: 4 | M47: =COUNTIF('Fleet Register'!$A:$A,A47) -> 0 | N47: (303) 527-1122 | P47: Andrew McKenna | Q47: https://www.milehighgliding.com/ | R47: 40.0394 | S47: -105.2261 | T47: 2026-09-22
A48: SSB | B48: Soaring Society of Boulder | C48: Club | D48: Mountain West | E48: Boulder Municipal (BDU) | F48: Boulder, CO | G48: Fly Friday night | H48: DEN + 0:45 | I48: Mountain thermal, wave | J48: Year-round | K48: Guest / short-term membership | L48: 7 | M48: =COUNTIF('Fleet Register'!$A:$A,A48) -> 4 | Q48: https://www.soarboulder.org/ | R48: 40.041 | S48: -105.224 | T48: 2026-09-22
A49: USA | B49: Utah Soaring Association / Soar Utah | C49: Club + commercial tow | D49: Mountain West | E49: Heber Valley (HCR) | F49: Heber City, UT | G49: Fly Friday night | H49: SLC + 0:55 (Tier C fares) | I49: High thermal, wave; May-Sep | J49: Seasonal | K49: Membership required | L49: 10 | M49: =COUNTIF('Fleet Register'!$A:$A,A49) -> 3 | N49: 801-979-8482 (CFI Lynn Alley) | P49: Lynn Alley (CFI); Dave Robinson, Soar Utah 801-580-9310 | Q49: https://utahsoaring.org/ | R49: 40.4818 | S49: -111.4288 | T49: 2026-09-22
A50: AZS | B50: Arizona Soaring (Estrella Sailport) | C50: Commercial | D50: Southwest | E50: Estrella Sailport (E68) | F50: Maricopa, AZ | G50: Fly Friday night | H50: PHX + 0:45 (Tier C fares) | I50: Desert thermal; best Oct-Apr | J50: Every day, year-round (short July break) | K50: Rents to visitors | L50: 1 | M50: =COUNTIF('Fleet Register'!$A:$A,A50) -> 8 | N50: (520) 568-2318 | O50: info@azsoaring.com | P50: Jason (jason@azsoaring.com) | Q50: https://azsoaring.com/ | R50: 33.0853 | S50: -112.161 | T50: 2026-09-22
A51: LVVSA | B51: Las Vegas Valley Soaring Association | C51: Club | D51: Southwest | E51: Jean (0L7) | F51: Jean, NV | G51: Fly Friday night | H51: LAS + 0:30 (Tier C fares) | I51: Thermal Mar-Nov; wave winter | J51: Weekends, year-round | K51: Membership required | L51: 9 | M51: =COUNTIF('Fleet Register'!$A:$A,A51) -> 4 | N51: 702-267-7499 (rides) | Q51: https://www.lvvsa.org/ | R51: 35.7683 | S51: -115.3296 | T51: 2026-09-22
A52: MERLIN | B52: Merlin Aviation | C52: Commercial | D52: Southwest | E52: Moriarty (0E0) | F52: Moriarty, NM | G52: Out of range | H52: ABQ + 0:45 (connection likely) | I52: Very strong thermal | J52: Call | K52: Unknown, call | M52: =COUNTIF('Fleet Register'!$A:$A,A52) -> 0 | N52: (505) 226-5556 | O52: info@merlinaviation.net | Q52: https://www.merlinaviation.net/ | R52: 34.9782 | S52: -106 | T52: 2026-09-22
A53: SOARNV | B53: SoaringNV | C53: Commercial | D53: Southwest | E53: Minden-Tahoe (MEV) | F53: Minden, NV | G53: Out of range | H53: No BOS nonstop to RNO | I53: Wave, thermal (world class) | J53: 7 days, year-round | K53: Rents to visitors | M53: =COUNTIF('Fleet Register'!$A:$A,A53) -> 0 | N53: (775) 790-8041 | Q53: https://soaringnv.com/ | R53: 39.0003 | S53: -119.7508 | T53: 2026-09-22

Sheet Rental Procedures
A1: ID | B1: Operator | C1: Rental status | D1: Procedure for a visiting licensed pilot | E1: Costs | F1: Tall-pilot notes | G1: Sources
A2: SUGAR | B2: Sugarbush Soaring | C2: Rents to visitors | D2: Publishes non-member glider rental rates (only such operator in New England). Checkout, currency and insurance rules not published (unverified): expect dual checkout in PW-6 or 2-33 plus site briefing. Ask whether a documented checkout stays valid for later visits. | E2: Non-member rental: PW-6U $169/h, 2-33 $85/h, 1-26E $79/h (20 min min). Non-member tow $28 + $3.30/100 ft (2,000 ft = $94). Instruction $59-86/h. Membership $875 share + $750/yr (YP 22-35: $175/yr). | F2: 2-33 roomy; PW-6 front seat fairly roomy (sit-test). | G2: https://sugarbushsoaring.com/doc/rate-sheet-2026.pdf ; https://sugarbushsoaring.com/about-us/fleet-aircraft
A3: GBSC | B3: Greater Boston Soaring Club (home club) | C3: Membership required | D3: Members only; no rental to non-members. Once rated: checkout in each two-seater (front and back seat) and a cockpit checkout before each single-seater. Club flights limited to 1 h. Visiting private owners only: Region 1 owners pay member tow rates; others $15/day temporary membership + $60 flat tow, max 5 visits/yr, SSA required. | E3: Regular $600 initiation (over 2 yr) + $750/yr; 90-day trial membership exists. Tow $14 hookup + $1.60/100 ft (min 1,200 ft). Instruction free. | F3: You do not fit the ASK-21. Sit-test the 1-34, L-23 and ASW-19 now; the 2-33 is roomy. | G3: https://www.soargbsc.net/index.php/gbsc_fleet ; https://www.soargbsc.net/fee_schedule
A4: MOHAWK | B4: Mohawk Soaring Club | C4: Guest / short-term membership | D4: No rental without membership. Advertises a short-term reduced-rate 'Limited membership'; $150 ride includes a 30-day limited membership with follow-up flights $50. Terms for rated pilots unverified: email ahead. | E4: Quarterly dues (amount unpublished); instruction free; club says average flight under $60. | F4: L-13 Blanik and 2-33 are roomy types. | G4: http://www.soarmohawk.com/membership/ ; FAA registry
A5: POSTMILLS | B5: Post Mills Soaring Club | C5: Membership required | D5: No visitor rental; full-season membership needed for solo. Trial membership ($100/flight, one-time) and temporary student membership exist. SSA required. Cottages on field. | E5: $450 initiation + $450/yr. Tow $18 + $10/1,000 ft. Glider use appears included in dues. Instruction free. | F5: L-23 Super Blanik and 2-33 are good tall-pilot types. | G5: https://flypmsc.org/ ; 2025 rates Google Doc
A6: NESA | B6: New England Soaring Association | C6: Membership required | D6: No visitor rental. Join (cheap), then checkout; short-notice flying once a member. | E6: $300 initiation + $300/yr + SSA. Gliders $10/flight. Tow $30 pattern to $70 at 5,000 ft. Instruction free. | F6: 2-33 and 1-34 likely fit. | G6: https://www.flynesa.com/about-us/our-fleet/ ; 2025 fee schedule PDF
A7: FRANCONIA | B7: Franconia Soaring Association | C7: Unknown, call | D7: Visitor rules unverified (membership pages blocked). Assume membership needed; call. Six CFIGs, first come first served. | E7: Rides $120 (3,000 ft) / $200 (5,000 ft). Membership rates not retrieved. | F7: Grob 103 Twin Astir is your best two-seat bet here; L-23 and 2-33 roomy. | G7: http://www.franconiasoaring.org/ ; FAA registry
A8: CSA | B8: Connecticut Soaring Association | C8: Membership required | D8: Must join; terms unpublished. Short of CFIGs and tow pilots. | E8: Not published. | F8: FAQ: cannot accommodate anyone over 6 ft 1 in / 220 lb (written for passengers). Poor fit. | G8: https://www.ctsoaring.org/our-fleet ; https://www.ctsoaring.org/faq
A9: GORHAM | B9: Mt Washington Wave Camp (GBSC/Franconia/Post Mills) | C9: Membership required | D9: An event, not an operator. Fly your own club's gliders; oxygen and wave-window checkouts apply. | E9: Per club. | F9: Per club fleet. | G9: https://www.soargbsc.com/wave/MtWashBrief.pdf
A10: SANFORD | B10: Sanford Soaring | C10: Closed / inactive | D10: Website not updated since 2019; no club-registered gliders found. Status unknown. | G10: Facebook page
A11: SPIRIT | B11: Spirit Soaring (motorglider rides) | C11: Closed / inactive | D11: Rides only in a Grob 109 motorglider; website no longer resolves. Not a rental option. | G11: Reviews to 2020
A12: WURTS | B12: Wurtsboro Airport / Wurtsboro Flight Mgmt | C12: Rents to visitors | D12: Public commercial rental. Rental-requirements page could not be read: expect instructor checkout, possibly minimum hours. Do one checkout day before relying on short-notice trips; ask currency rule. | E12: Rental: Grob 103 $75/h, 2-33 $67/h, 1-26E $55/h. Tow to 2,500 ft $74.07, +$20/1,000 ft. Instruction $65-67/h. | F12: 2-33 good; Grob 103 depends on proportions; 1-26 poor. | G12: https://www.wurtsboroairport.com/rates
A13: VANSANT | B13: Van Sant Airport / Bird of Paradise | C13: Rents to visitors | D13: 'Licensed glider pilots may also rent.' Checkout/currency rules not published; expect a checkout. | E13: Rental 2-33 $80/h, 2-32 $80/h + tows. Tow $50 (1,000) / $60 (2,000) / $65 (3,000) / $100 (5,000). Instruction $120 + tow. | F13: 2-33 and 2-32 both roomy. | G13: https://vansantairport.com/rides-and-rental-prices/
A14: HHSC | B14: Harris Hill Soaring Corp | C14: Guest / short-term membership | D14: 'Board approved guest' category: $20/day, rental $50/h. Email ahead for guest approval; checkout in 2-33, 1-34 or Duo Discus. Non-members: tows only. | E14: Guest $20/day; rental $50/h; tow $20 + $30/1,000 ft. Senior member $300 + $30/mo; rental $9-25/h. | F14: 2-33 and Duo Discus good; ASK-21 no. | G14: https://harrishillsoaring.org/wp-content/uploads/2026/02/2026-rates.pdf
A15: PSA | B15: Pittsburgh Soaring Association | C15: Guest / short-term membership | D15: 'Temporary memberships are available for visiting pilots' (price unpublished). | E15: Rental $10/h; tow $25 + $5/1,000 ft; full $60/mo + ~$500 buy-in. | F15: Grob 102 and L-23 good. | G15: http://pghsoar.org/fly-with-us/
A16: ASA | B16: Adirondack Soaring Association | C16: Guest / short-term membership | D16: Long-Distance membership (live 120+ mi away): full fleet access; book on Click N Glide. Board approval + SSA. Checkout Grob 103 then Grob 102. | E16: Long-Distance $650 initiation + $15/month; gliders + instruction included; tows only ($40 to 2,000 ft, 2022). | F16: All-Grob fleet: Grob 102 roomiest; Grob 103 depends on proportions. | G16: https://www.adirondacksoaring.com/membership
A17: ACA | B17: Aero Club Albatross | C17: Membership required | D17: Full membership (licensed pilots): apply, attend a monthly meeting (3rd Thu, Denville NJ), wing-runner course, checkout. No hourly glider charge afterwards. | E17: $1,000 initiation (or $250/yr x4) + $138 dues + $530/yr flight fee + SSA. Tow 2,000 ft $38 with season pass. | F17: 2-33 and LS-4 good; Twin Astir depends on proportions. | G17: https://www.aeroclubalbatross.org/memberships/
A18: FLSC | B18: Finger Lakes Soaring Club | C18: Guest / short-term membership | D18: Long Distance membership; 'Guest' status for pilots of other SSA clubs (orientation). Seasonal check ride; 1-26 needs 15 flights in type. | E18: Long Distance $550 ($200 refundable) + $15/mo. Tow $18/1,000 ft; winch $8.50. | F18: Grob 102 and 2-33 good. | G18: https://flsc.org/MembershipJoinUs.php
A19: JRS | B19: Jersey Ridge Soaring | C19: Unknown, call | D19: Website lists tows for private owners and ACA members; no solo-rental policy published. Call about checkout + rental of 2-33 / 1-26. | E19: Lessons $130-160. | F19: 2-33 and 2-32 good. | G19: http://www.jerseyridgesoaring.com/Lessons.html
A20: BSA | B20: Brandywine Soaring Association | C20: Guest / short-term membership | D20: Non-resident membership (100+ mi); waiting list, faster for rated pilots. | E20: $500 + $35/mo; tow 3,000 ft $44. | F20: L-23 roomy; ASK-21 no. | G20: brandywinesoaring.org membership page
A21: VSC | B21: Valley Soaring Club | C21: Unknown, call | D21: Membership terms unpublished; call. | F21: 2-33 good. | G21: FlightSchoolList; FAA registry
A22: PGC | B22: Philadelphia Glider Council | C22: Membership required | D22: Full membership only. | E22: $1,090/yr + $700 entry + $100 bond; tows ~$35. | F22: Grob 102 roomy; Grob 103s depend on proportions. | G22: https://pgcsoaring.org/glider-club-membership.php
A23: TIGERS | B23: Soaring Tigers | C23: Membership required | D23: Annual membership only; tows only after that. | E23: $700/yr after solo; tows $35-90. | F23: Pilot weight limits 191-385 lb by glider. | G23: https://soaringtigers.org/memberinfo.html
A24: LISA | B24: Long Island Soaring Association | C24: Membership required | D24: 3 prepaid guest flights + 2 meetings before joining. Poor fit for chasing lift. | E24: Guest flight $120 then $60; $800 + $66/mo; tow $21 to 1,000 ft. | F24: 2-33 good. | G24: https://longislandsoaring.com/fees
A25: SKYLINE | B25: Skyline Soaring Club | C25: Guest / short-term membership | D25: 'Visiting Member' $10/day for members of SSA-affiliated clubs, max 5 days/yr. Introductory $75 for 45 days. Email with SSA number + logbook; expect checkout. | E25: ASK-21 $39/h, Discus CS $36/h (capped 3 h), PW-5 $24/h. Tow $30 to 1,000 ft + $1/100 ft. | F25: ASK-21 won't fit; Discus CS medium (sit-test). | G25: https://www.skylinesoaring.org/cms/ssc-documents/dues-fees/
A26: BRSS | B26: Blue Ridge Soaring Society | C26: Guest / short-term membership | D26: Monthly guest memberships, club approval. Tows and instruction members only. | E26: Unpublished. | F26: ASK-21, LS-4, LS-6: poor fit. | G26: https://www.brss.net/visitor-info/
A27: SVS | B27: Shenandoah Valley Soaring | C27: Guest / short-term membership | D27: 3-month introductory membership (from demo flight). Height limit under 6'5", 230 lb. | E27: Unpublished. | F27: Under 6'5" limit. | G27: https://www.svsoar.org/faqs.html
A28: MASA | B28: Mid-Atlantic Soaring Association | C28: Membership required | D28: Full membership, provisional first year, 5 duty days. No visitor membership. Pilot weight ~154-240 lb. | E28: $1,000 initiation + $695/yr + SSA. | F28: Mostly ASK-21; 2-33A only likely fit. | G28: midatlanticsoaring.org join page
A29: ESC | B29: Eastern Soaring Center | C29: Closed / inactive | D29: Rents to rated pilots with an ESC airfield/winch checkride in last 12 months. Closed for 2026 season; watch for 2027. | E29: ASK-13 $55/h; winch $30-60. | F29: ASK-13 roomy. | G29: https://www.easternsoaringcenter.com/
A30: TSS | B30: Tidewater Soaring Society | C30: Membership required | D30: Membership only. | E30: $300 + $200 deposit + $45/mo + SSA. | F30: 2-33A good. | G30: http://www.tidewatersoaring.org/membership.html
A31: CHIL | B31: Chilhowee Gliderport | C31: Rents to visitors | D31: Commercial hourly rental, no membership. Expect dual checkout (2-33A) first visit. Block account $1,000 buys $1,100 credit (forfeited after 1 yr idle). After that, call Thursday. | E31: 2-33A $48/h, PW-6U $72/h, 1-26E $40/h, PW-5 $48/h (15 min min). Tow $20 + $2/100 ft ($40 min). Instruction $60/h. | F31: 2-33A best; PW-6U fairly roomy; 2-32 very roomy (dual only). | G31: https://www.chilhowee.com/rates.html
A32: BHS | B32: Bermuda High Soaring | C32: Unknown, call | D32: 'Not scheduling instruction at this time'; members first. Call about rental. | E32: Ride $120 (2-33); weight limit 230-240 lb. | F32: 2-33 and Duo Discus good. | G32: https://bermudahighsoaring.com/contact-us.html
A33: CAROLINA | B33: Carolina Soaring Association | C33: Membership required | D33: Contact before a trip; no visitor option published. | E33: $250 + $82/mo; gliders $0/h; aerotow $7 + $2.17/100 ft; winch $12. | F33: Grob 103 roomy. | G33: https://carolinasoaring.org/rates/
A34: NCSA | B34: North Carolina Soaring Association | C34: Membership required | D34: 'Drop by anytime we are flying'; fleet and rates unpublished. | G34: https://soaringnc.org/
A35: MGSA | B35: Mid-Georgia Soaring Association | C35: Membership required | D35: Membership only. | E35: $500 + $450/yr + $500 capital note + SSA; tow 2,000 ft ~$50. | F35: ASK-21s; Grob 102 maybe. | G35: https://www.soar-mgsa.org/membershipinfo
A36: EAGLEVILLE | B36: Eagleville Soaring Club | C36: Membership required | D36: No visitor option published. | F36: ASK-21s, LS-4: poor fit ('height limited if significantly above 6 ft'). | G36: https://eaglevillesoaring.org/
A37: SANDHILL | B37: Sandhill Soaring Club | C37: Guest / short-term membership | D37: 'Short-term Guest Membership may be arranged for licensed soaring pilots.' Price unpublished. | E37: Tow min $26 + $1/100 ft above 1,000 ft. | F37: DG-505, Grob 103, 2-33: best tall-pilot club fleet. | G37: https://www.sandhillsoaring.org/join
A38: SKYSOAR | B38: Sky Soaring | C38: Membership required | D38: Accepting 1 new member this season; no visitor option. | E38: $250 + $725/yr + $1,000 buy-in; tows $25-55. | F38: 2-33A, KR-03 Puchatek good. | G38: https://skysoaring.com/membership/
A39: CGC | B39: Chicago Glider Club | C39: Membership required | D39: Sponsor required; long-term commitment. | E39: $1,200 + $552/yr; ships $36-40/h. | F39: Duo Discus front seat roomy. | G39: chicagogliderclub.org fees
A40: CCSC | B40: Caesar Creek Soaring Club | C40: Membership required | D40: Full membership required to act as PIC. | E40: $1,000 + $38/mo + 12 SSD shares ($100 ea). | F40: 2-33s, Grob 102. | G40: https://www.soarccsc.com/membership/
A41: SEMINOLE | B41: Seminole-Lake Gliderport | C41: Rents to visitors | D41: By schedule only; call ahead. Renters must carry $40,000 hull insurance. Checkout rules unpublished. Gliderport listed for sale (small continuity risk). | E41: Grob 103 $125/h, L-23 $120/h. Tow rates on request. Rides $180-260. | F41: L-23 and Grob 103 good. | G41: https://www.soarfl.com/airfield_info/ ; https://www.soarfl.com/our_aircraft
A42: MIAMI | B42: Miami Gliders | C42: Rents to visitors | D42: Solo rental rates published; requirements not. Call about insurance + checkout. | E42: L-23 $90/h, 2-32 $90/h, B-4 $75/h. Tow $55 (2,000 ft) to $75 (3,000 ft). | F42: L-23 and 2-32 good. | G42: https://www.miamigliders.com/rates.html
A43: TBSS | B43: Tampa Bay Soaring Society | C43: Membership required | D43: Apply in person; full membership only. | E43: $800 + $250/6 mo; tow $20 + $1/100 ft; gliders free. | F43: L-23s good. | G43: https://www.tampabaysoaring.com/membership/
A44: TSA | B44: Texas Soaring Association | C44: Guest / short-term membership | D44: Visiting Licensed Pilot Membership (under 30 days); SSA + glider rating. Details in members memo. Also $30 Texas XC Series = temporary member at participating clubs. | E44: Full $500 + $65/mo. | F44: ASK-21, PW-5, 1-26: poor fit; Duo Discus maybe. | G44: https://texassoaring.org/page-18133
A45: SCH | B45: Soaring Club of Houston | C45: Guest / short-term membership | D45: 'Guest' and 'One-Day' memberships exist; ask what they allow. | E45: 2-33 $0.20/min; L-23/L-33 $0.40/min; ASK-21 $0.60/min. | F45: L-23 and 2-33 good. | G45: SCH membership information page
A46: FLF | B46: Fault Line Flyers | C46: Guest / short-term membership | D46: Guest membership at $46/mo for pilots from other clubs; but site says club aircraft not for non-members. Confirm. | E46: Tows $25-55; Schweizers $0.25/min; Twin Astir $0.30/min. | F46: 2-33 good. | G46: https://www.faultlineflyers.com/
A47: MHG | B47: Mile High Gliding | C47: Rents to visitors | D47: 'Rentals' advertised; fleet/terms not online. Expect mountain + density-altitude checkout and own insurance. Call. | E47: Not published. | F47: Unknown; back seat reported tight. | G47: Boulder Chamber listing
A48: SSB | B48: Soaring Society of Boulder | C48: Guest / short-term membership | D48: 'Limited' membership (no initiation). Provisional until you attend a meeting; flight + written + oral checks. Book via Flightlog. | E48: Limited: $21/flight + $36/h. Regular $500 + $500 deposit + ~$41/mo. | F48: DG-505 best chance; ASK-21 no. | G48: https://www.soarboulder.org/aircraft
... A51: LVVSA | B51: Las Vegas Valley Soaring Association | C51: Membership required | D51: Join (a year's dues + SSA). No temporary membership. | E51: $72.50/mo; tows from $42.50. | F51: 2-33A and L-23 good. | G51: https://www.lvvsa.org/new-members
A52: MERLIN | B52: Merlin Aviation | C52: Unknown, call | D52: AirNav lists rental; terms unpublished. | E52: Rides from $200. | G52: https://www.merlinaviation.net/
A53: SOARNV | B53: SoaringNV | C53: Rents to visitors | D53: Renter's insurance proof; XC checkout before leaving glide range. Reference only (no Friday-night access). | F53: Duo Discus/Duo X. | G53: https://soaringnv.com/wp-content/uploads/2019/11/2020-RENTAL-AGREEMENT.pdf

Sheet Glider Types
A1: Type key | B1: Type | C1: Class | D1: Seats | E1: Span (m) | F1: Max L/D | G1: Best-glide speed (kt) | H1: Min sink (fpm) | I1: Vne (kt) | J1: Cockpit / tall pilot | K1: Figures approximate?
A2: 2-33 | B2: Schweizer SGS 2-33A | C2: Trainer (metal) | D2: 2 | E2: 15.5 | F2: 23 | G2: 39 | H2: 185 | I2: 85 | J2: Roomy | K2: No
A3: 2-32 | B3: Schweizer SGS 2-32 | C3: Two-seat (metal) | D3: 3 | E3: 17.4 | F3: 34 | G3: 51 | H3: 144 | I3: 137 | J3: Roomy | K3: No
A4: 2-22 | B4: Schweizer SGU 2-22 | C4: Trainer (vintage) | D4: 2 | E4: 13.4 | F4: 17 | G4: 42 | H4: 197 | I4: 63 | J4: Tight | K4: Yes, verify
A5: 1-26 | B5: Schweizer SGS 1-26 | C5: One-design (metal) | D5: 1 | E5: 12.2 | F5: 23 | G5: 46 | H5: 161 | I5: 99 | J5: Tight headroom | K5: No
A6: 1-34 | B6: Schweizer SGS 1-34 | C6: Standard (metal) | D6: 1 | E6: 15 | F6: 34 | G6: 46 | H6: 132 | I6: 114 | J6: OK | K6: No
A7: 1-35 | B7: Schweizer SGS 1-35 | C7: 15 m (metal) | D7: 1 | E7: 15 | F7: 38 | G7: 52 | H7: 120 | I7: 130 | J7: Reclined, check | K7: Yes, verify
A8: 1-36 | B8: Schweizer SGS 1-36 Sprite | C8: Sport (metal) | D8: 1 | E8: 14.1 | F8: 31 | G8: 46 | H8: 132 | I8: 105 | J8: OK | K8: Yes, verify
A9: 1-23 | B9: Schweizer SGS 1-23 | C9: Standard (vintage metal) | D9: 1 | E9: 15.2 | F9: 29 | G9: 43 | H9: 138 | I9: 121 | J9: Unknown | K9: Yes, verify
A10: L-23 | B10: LET L-23 Super Blanik | C10: Trainer (metal) | D10: 2 | E10: 16.2 | F10: 28 | G10: 49 | H10: 148 | I10: 135 | J10: Roomy | K10: No
A11: L-13 | B11: LET L-13 Blanik | C11: Trainer (metal) | D11: 2 | E11: 16.2 | F11: 28 | G11: 46 | H11: 161 | I11: 137 | J11: Roomy | K11: No
A12: L-33 | B12: LET L-33 Solo | C12: Club (metal) | D12: 1 | E12: 14.1 | F12: 34 | G12: 46 | H12: 130 | I12: 135 | J12: OK | K12: Yes, verify
A13: ASK-21 | B13: Schleicher ASK-21 | C13: Two-seat trainer (GRP) | D13: 2 | E13: 17 | F13: 34 | G13: 49 | H13: 128 | I13: 151 | J13: Tight for very tall (did not fit Martin) | K13: No
... A35: CIRRUS | B35: Schempp-Hirth Open Cirrus | C35: Open (GRP, vintage) | D35: 1 | E35: 17.7 | F35: 44 | G35: 51 | H35: 108 | I35: 119 | J35: Unknown | K35: Yes, verify
A37: Nominal type figures (manufacturer data / type references). L/D = maximum glide ratio; Vne = never-exceed speed; min sink = lowest still-air sink rate. Always use the actual aircraft's flight manual.

Sheet Fleet Register
A1: Operator ID | B1: Operator | C1: Glider | D1: Type key | E1: Registration (N-number) | F1: Seats | G1: Rate | H1: Who can fly it | I1: Tall-pilot note | J1: Max L/D | K1: Best-glide kt | L1: Min sink fpm | M1: Vne kt | N1: Sat in it? (Y/N) | O1: My checkout date | P1: Notes
A2: GBSC | B2: Greater Boston Soaring Club (home club) | C2: Schleicher ASK-21 | D2: ASK-21 | E2: N421GB | F2: 2 | G2: $25/h members | H2: Members | I2: Did not fit you | J2: =IFERROR(INDEX('Glider Types'!$F:$F,MATCH(D2,'Glider Types'!$A:$A,0)),"") -> 34 | K2: =IFERROR(INDEX('Glider Types'!$G:$G,MATCH(D2,'Glider Types'!$A:$A,0)),"") -> 49 | L2: =IFERROR(INDEX('Glider Types'!$H:$H,MATCH(D2,'Glider Types'!$A:$A,0)),"") -> 128 | M2: =IFERROR(INDEX('Glider Types'!$I:$I,MATCH(D2,'Glider Types'!$A:$A,0)),"") -> 151
A3: GBSC | B3: Greater Boston Soaring Club (home club) | C3: Schleicher ASK-21 | D3: ASK-21 | E3: N721RC | F3: 2 | G3: $25/h members | H3: Members | I3: Did not fit you | J3: =IFERROR(INDEX('Glider Types'!$F:$F,MATCH(D3,'Glider Types'!$A:$A,0)),"") -> 34 | K3: =IFERROR(INDEX('Glider Types'!$G:$G,MATCH(D3,'Glider Types'!$A:$A,0)),"") -> 49 | L3: =IFERROR(INDEX('Glider Types'!$H:$H,MATCH(D3,'Glider Types'!$A:$A,0)),"") -> 128 | M3: =IFERROR(INDEX('Glider Types'!$I:$I,MATCH(D3,'Glider Types'!$A:$A,0)),"") -> 151
A4: GBSC | B4: Greater Boston Soaring Club (home club) | C4: Schweizer 2-33A | D4: 2-33 | E4: N1225S | F4: 2 | G4: $14/h members | H4: Members | I4: Roomy | J4: =IFERROR(INDEX('Glider Types'!$F:$F,MATCH(D4,'Glider Types'!$A:$A,0)),"") -> 23 | K4: =IFERROR(INDEX('Glider Types'!$G:$G,MATCH(D4,'Glider Types'!$A:$A,0)),"") -> 39 | L4: =IFERROR(INDEX('Glider Types'!$H:$H,MATCH(D4,'Glider Types'!$A:$A,0)),"") -> 185 | M4: =IFERROR(INDEX('Glider Types'!$I:$I,MATCH(D4,'Glider Types'!$A:$A,0)),"") -> 85
A5: GBSC | B5: Greater Boston Soaring Club (home club) | C5: LET L-23 Super Blanik | D5: L-23 | E5: not found | F5: 2 | G5: $14/h members | H5: Members | I5: Roomy; sit-test | J5: =IFERROR(INDEX('Glider Types'!$F:$F,MATCH(D5,'Glider Types'!$A:$A,0)),"") -> 28 | K5: =IFERROR(INDEX('Glider Types'!$G:$G,MATCH(D5,'Glider Types'!$A:$A,0)),"") -> 49 | L5: =IFERROR(INDEX('Glider Types'!$H:$H,MATCH(D5,'Glider Types'!$A:$A,0)),"") -> 148 | M5: =IFERROR(INDEX('Glider Types'!$I:$I,MATCH(D5,'Glider Types'!$A:$A,0)),"") -> 135
A6: GBSC | B6: Greater Boston Soaring Club (home club) | C6: Schleicher ASW-19B | D6: ASW-19 | E6: not found | F6: 1 | G6: $20/h, 2 h limit | H6: Members | I6: Tight above ~6'2" | J6: =IFERROR(INDEX('Glider Types'!$F:$F,MATCH(D6,'Glider Types'!$A:$A,0)),"") -> 38.5 | K6: =IFERROR(INDEX('Glider Types'!$G:$G,MATCH(D6,'Glider Types'!$A:$A,0)),"") -> 54 | L6: =IFERROR(INDEX('Glider Types'!$H:$H,MATCH(D6,'Glider Types'!$A:$A,0)),"") -> 118 | M6: =IFERROR(INDEX('Glider Types'!$I:$I,MATCH(D6,'Glider Types'!$A:$A,0)),"") -> 138
A7: GBSC | B7: Greater Boston Soaring Club (home club) | C7: LET L-33 Solo | D7: L-33 | E7: not found | F7: 1 | G7: $10/h, 2 h limit | H7: Members | I7: Probably OK | J7: =IFERROR(INDEX('Glider Types'!$F:$F,MATCH(D7,'Glider Types'!$A:$A,0)),"") -> 34 | K7: =IFERROR(INDEX('Glider Types'!$G:$G,MATCH(D7,'Glider Types'!$A:$A,0)),"") -> 46 | L7: =IFERROR(INDEX('Glider Types'!$H:$H,MATCH(D7,'Glider Types'!$A:$A,0)),"") -> 130 | M7: =IFERROR(INDEX('Glider Types'!$I:$I,MATCH(D7,'Glider Types'!$A:$A,0)),"") -> 135
A8: GBSC | B8: Greater Boston Soaring Club (home club) | C8: Schweizer 1-34 | D8: 1-34 | E8: N1156S | F8: 1 | G8: $10/h | H8: Members | I8: Generally good | J8: =IFERROR(INDEX('Glider Types'!$F:$F,MATCH(D8,'Glider Types'!$A:$A,0)),"") -> 34 | K8: =IFERROR(INDEX('Glider Types'!$G:$G,MATCH(D8,'Glider Types'!$A:$A,0)),"") -> 46 | L8: =IFERROR(INDEX('Glider Types'!$H:$H,MATCH(D8,'Glider Types'!$A:$A,0)),"") -> 132 | M8: =IFERROR(INDEX('Glider Types'!$I:$I,MATCH(D8,'Glider Types'!$A:$A,0)),"") -> 114
A9: GBSC | B9: Greater Boston Soaring Club (home club) | C9: Schweizer 1-26E | D9: 1-26 | E9: N33917 | F9: 1 | G9: $10/h | H9: Members | I9: Small | J9: =IFERROR(INDEX('Glider Types'!$F:$F,MATCH(D9,'Glider Types'!$A:$A,0)),"") -> 23 | K9: =IFERROR(INDEX('Glider Types'!$G:$G,MATCH(D9,'Glider Types'!$A:$A,0)),"") -> 46 | L9: =IFERROR(INDEX('Glider Types'!$H:$H,MATCH(D9,'Glider Types'!$A:$A,0)),"") -> 161 | M9: =IFERROR(INDEX('Glider Types'!$I:$I,MATCH(D9,'Glider Types'!$A:$A,0)),"") -> 99
A10: SUGAR | B10: Sugarbush Soaring | C10: PZL PW-6U | D10: PW-6 | E10: N16VT | F10: 2 | G10: $169/h non-member; $50 member | H10: Yes | I10: Front seat fairly roomy | J10: =IFERROR(INDEX('Glider Types'!$F:$F,MATCH(D10,'Glider Types'!$A:$A,0)),"") -> 34 | K10: =IFERROR(INDEX('Glider Types'!$G:$G,MATCH(D10,'Glider Types'!$A:$A,0)),"") -> 51 | L10: =IFERROR(INDEX('Glider Types'!$H:$H,MATCH(D10,'Glider Types'!$A:$A,0)),"") -> 146 | M10: =IFERROR(INDEX('Glider Types'!$I:$I,MATCH(D10,'Glider Types'!$A:$A,0)),"") -> 140
A11: SUGAR | B11: Sugarbush Soaring | C11: PZL PW-6U | D11: PW-6 | E11: N777VT | F11: 2 | G11: $169/h non-member; $50 member | H11: Yes | I11: Front seat fairly roomy | J11: =IFERROR(INDEX('Glider Types'!$F:$F,MATCH(D11,'Glider Types'!$A:$A,0)),"") -> 34 | K11: =IFERROR(INDEX('Glider Types'!$G:$G,MATCH(D11,'Glider Types'!$A:$A,0)),"") -> 51 | L11: =IFERROR(INDEX('Glider Types'!$H:$H,MATCH(D11,'Glider Types'!$A:$A,0)),"") -> 146 | M11: =IFERROR(INDEX('Glider Types'!$I:$I,MATCH(D11,'Glider Types'!$A:$A,0)),"") -> 140
A12: SUGAR | B12: Sugarbush Soaring | C12: Schweizer 2-33 | D12: 2-33 | E12: N2743H | F12: 2 | G12: $85/h non-member; $40 member | H12: Yes | I12: Roomy | J12: =IFERROR(INDEX('Glider Types'!$F:$F,MATCH(D12,'Glider Types'!$A:$A,0)),"") -> 23 | K12: =IFERROR(INDEX('Glider Types'!$G:$G,MATCH(D12,'Glider Types'!$A:$A,0)),"") -> 39 | L12: =IFERROR(INDEX('Glider Types'!$H:$H,MATCH(D12,'Glider Types'!$A:$A,0)),"") -> 185 | M12: =IFERROR(INDEX('Glider Types'!$I:$I,MATCH(D12,'Glider Types'!$A:$A,0)),"") -> 85
A13: SUGAR | B13: Sugarbush Soaring | C13: Schweizer 2-33 | D13: 2-33 | E13: not found | F13: 2 | G13: $85/h non-member; $40 member | H13: Yes | I13: Roomy | J13: =IFERROR(INDEX('Glider Types'!$F:$F,MATCH(D13,'Glider Types'!$A:$A,0)),"") -> 23 | K13: =IFERROR(INDEX('Glider Types'!$G:$G,MATCH(D13,'Glider Types'!$A:$A,0)),"") -> 39 | L13: =IFERROR(INDEX('Glider Types'!$H:$H,MATCH(D13,'Glider Types'!$A:$A,0)),"") -> 185 | M13: =IFERROR(INDEX('Glider Types'!$I:$I,MATCH(D13,'Glider Types'!$A:$A,0)),"") -> 85
A14: SUGAR | B14: Sugarbush Soaring | C14: Schweizer 1-26E | D14: 1-26 | E14: N1107S | F14: 1 | G14: $79/h non-member; $40 member | H14: Yes | I14: Small | J14: =IFERROR(INDEX('Glider Types'!$F:$F,MATCH(D14,'Glider Types'!$A:$A,0)),"") -> 23 | K14: =IFERROR(INDEX('Glider Types'!$G:$G,MATCH(D14,'Glider Types'!$A:$A,0)),"") -> 46 | L14: =IFERROR(INDEX('Glider Types'!$H:$H,MATCH(D14,'Glider Types'!$A:$A,0)),"") -> 161 | M14: =IFERROR(INDEX('Glider Types'!$I:$I,MATCH(D14,'Glider Types'!$A:$A,0)),"") -> 99
A15: MOHAWK | B15: Mohawk Soaring Club | C15: LET L-13 Blanik | D15: L-13 | E15: N336MS | F15: 2 | H15: Members | I15: Roomy | J15: =IFERROR(INDEX('Glider Types'!$F:$F,MATCH(D15,'Glider Types'!$A:$A,0)),"") -> 28 | K15: =IFERROR(INDEX('Glider Types'!$G:$G,MATCH(D15,'Glider Types'!$A:$A,0)),"") -> 46 | L15: =IFERROR(INDEX('Glider Types'!$H:$H,MATCH(D15,'Glider Types'!$A:$A,0)),"") -> 161 | M15: =IFERROR(INDEX('Glider Types'!$I:$I,MATCH(D15,'Glider Types'!$A:$A,0)),"") -> 137
A16: MOHAWK | B16: Mohawk Soaring Club | C16: Schweizer 2-33A | D16: 2-33 | E16: N1186S | F16: 2 | H16: Members | I16: Roomy | J16: =IFERROR(INDEX('Glider Types'!$F:$F,MATCH(D16,'Glider Types'!$A:$A,0)),"") -> 23 | K16: =IFERROR(INDEX('Glider Types'!$G:$G,MATCH(D16,'Glider Types'!$A:$A,0)),"") -> 39 | L16: =IFERROR(INDEX('Glider Types'!$H:$H,MATCH(D16,'Glider Types'!$A:$A,0)),"") -> 185 | M16: =IFERROR(INDEX('Glider Types'!$I:$I,MATCH(D16,'Glider Types'!$A:$A,0)),"") -> 85
A17: MOHAWK | B17: Mohawk Soaring Club | C17: Schweizer 2-33A | D17: 2-33 | E17: N2039T | F17: 2 | H17: Members | I17: Roomy | J17: =IFERROR(INDEX('Glider Types'!$F:$F,MATCH(D17,'Glider Types'!$A:$A,0)),"") -> 23 | K17: =IFERROR(INDEX('Glider Types'!$G:$G,MATCH(D17,'Glider Types'!$A:$A,0)),"") -> 39 | L17: =IFERROR(INDEX('Glider Types'!$H:$H,MATCH(D17,'Glider Types'!$A:$A,0)),"") -> 185 | M17: =IFERROR(INDEX('Glider Types'!$I:$I,MATCH(D17,'Glider Types'!$A:$A,0)),"") -> 85
A18: MOHAWK | B18: Mohawk Soaring Club | C18: Schweizer 2-22E | D18: 2-22 | E18: N2729Z | F18: 2 | H18: Members | I18: Small; may be inactive | J18: =IFERROR(INDEX('Glider Types'!$F:$F,MATCH(D18,'Glider Types'!$A:$A,0)),"") -> 17 | K18: =IFERROR(INDEX('Glider Types'!$G:$G,MATCH(D18,'Glider Types'!$A:$A,0)),"") -> 42 | L18: =IFERROR(INDEX('Glider Types'!$H:$H,MATCH(D18,'Glider Types'!$A:$A,0)),"") -> 197 | M18: =IFERROR(INDEX('Glider Types'!$I:$I,MATCH(D18,'Glider Types'!$A:$A,0)),"") -> 63
A19: MOHAWK | B19: Mohawk Soaring Club | C19: Schweizer 1-26E | D19: 1-26 | E19: N65947 | F19: 1 | H19: Members | I19: Small | J19: =IFERROR(INDEX('Glider Types'!$F:$F,MATCH(D19,'Glider Types'!$A:$A,0)),"") -> 23 | K19: =IFERROR(INDEX('Glider Types'!$G:$G,MATCH(D19,'Glider Types'!$A:$A,0)),"") -> 46 | L19: =IFERROR(INDEX('Glider Types'!$H:$H,MATCH(D19,'Glider Types'!$A:$A,0)),"") -> 161 | M19: =IFERROR(INDEX('Glider Types'!$I:$I,MATCH(D19,'Glider Types'!$A:$A,0)),"") -> 99
A20: MOHAWK | B20: Mohawk Soaring Club | C20: Schweizer 1-23H-15 | D20: 1-23 | E20: N10388 | F20: 1 | H20: Members | I20: Small; may be inactive | J20: =IFERROR(INDEX('Glider Types'!$F:$F,MATCH(D20,'Glider Types'!$A:$A,0)),"") -> 29 | K20: =IFERROR(INDEX('Glider Types'!$G:$G,MATCH(D20,'Glider Types'!$A:$A,0)),"") -> 43 | L20: =IFERROR(INDEX('Glider Types'!$H:$H,MATCH(D20,'Glider Types'!$A:$A,0)),"") -> 138 | M20: =IFERROR(INDEX('Glider Types'!$I:$I,MATCH(D20,'Glider Types'!$A:$A,0)),"") -> 121
A21: POSTMILLS | B21: Post Mills Soaring Club | C21: Schweizer 2-33A | D21: 2-33 | E21: N17967 | F21: 2 | G21: In dues | H21: Members | I21: Roomy | J21: =IFERROR(INDEX('Glider Types'!$F:$F,MATCH(D21,'Glider Types'!$A:$A,0)),"") -> 23 | K21: =IFERROR(INDEX('Glider Types'!$G:$G,MATCH(D21,'Glider Types'!$A:$A,0)),"") -> 39 | L21: =IFERROR(INDEX('Glider Types'!$H:$H,MATCH(D21,'Glider Types'!$A:$A,0)),"") -> 185 | M21: =IFERROR(INDEX('Glider Types'!$I:$I,MATCH(D21,'Glider Types'!$A:$A,0)),"") -> 85
A22: POSTMILLS | B22: Post Mills Soaring Club | C22: LET L-23 Super Blanik | D22: L-23 | E22: N303BA | F22: 2 | G22: In dues | H22: Members | I22: Roomy | J22: =IFERROR(INDEX('Glider Types'!$F:$F,MATCH(D22,'Glider Types'!$A:$A,0)),"") -> 28 | K22: =IFERROR(INDEX('Glider Types'!$G:$G,MATCH(D22,'Glider Types'!$A:$A,0)),"") -> 49 | L22: =IFERROR(INDEX('Glider Types'!$H:$H,MATCH(D22,'Glider Types'!$A:$A,0)),"") -> 148 | M22: =IFERROR(INDEX('Glider Types'!$I:$I,MATCH(D22,'Glider Types'!$A:$A,0)),"") -> 135
A23: POSTMILLS | B23: Post Mills Soaring Club | C23: Schweizer 1-26E | D23: 1-26 | E23: N1115S | F23: 1 | G23: In dues | H23: Members | I23: Small | J23: =IFERROR(INDEX('Glider Types'!$F:$F,MATCH(D23,'Glider Types'!$A:$A,0)),"") -> 23 | K23: =IFERROR(INDEX('Glider Types'!$G:$G,MATCH(D23,'Glider Types'!$A:$A,0)),"") -> 46 | L23: =IFERROR(INDEX('Glider Types'!$H:$H,MATCH(D23,'Glider Types'!$A:$A,0)),"") -> 161 | M23: =IFERROR(INDEX('Glider Types'!$I:$I,MATCH(D23,'Glider Types'!$A:$A,0)),"") -> 99
A24: POSTMILLS | B24: Post Mills Soaring Club | C24: HpH 304C | D24: HPH304 | E24: N304PM | F24: 1 | G24: In dues | H24: Members | I24: Unverified | J24: =IFERROR(INDEX('Glider Types'!$F:$F,MATCH(D24,'Glider Types'!$A:$A,0)),"") -> 43 | K24: =IFERROR(INDEX('Glider Types'!$G:$G,MATCH(D24,'Glider Types'!$A:$A,0)),"") -> 57 | L24: =IFERROR(INDEX('Glider Types'!$H:$H,MATCH(D24,'Glider Types'!$A:$A,0)),"") -> 114 | M24: =IFERROR(INDEX('Glider Types'!$I:$I,MATCH(D24,'Glider Types'!$A:$A,0)),"") -> 146
A25: NESA | B25: New England Soaring Association | C25: Schweizer 2-33 | D25: 2-33 | E25: N2041T | F25: 2 | G25: $10/flight | H25: Members | J25: =IFERROR(INDEX('Glider Types'!$F:$F,MATCH(D25,'Glider Types'!$A:$A,0)),"") -> 23 | K25: =IFERROR(INDEX('Glider Types'!$G:$G,MATCH(D25,'Glider Types'!$A:$A,0)),"") -> 39 | L25: =IFERROR(INDEX('Glider Types'!$H:$H,MATCH(D25,'Glider Types'!$A:$A,0)),"") -> 185 | M25: =IFERROR(INDEX('Glider Types'!$I:$I,MATCH(D25,'Glider Types'!$A:$A,0)),"") -> 85
A26: NESA | B26: New England Soaring Association | C26: Schweizer 2-33A | D26: 2-33 | E26: N1242S | F26: 2 | G26: $10/flight | H26: Members | J26: =IFERROR(INDEX('Glider Types'!$F:$F,MATCH(D26,'Glider Types'!$A:$A,0)),"") -> 23 | K26: =IFERROR(INDEX('Glider Types'!$G:$G,MATCH(D26,'Glider Types'!$A:$A,0)),"") -> 39 | L26: =IFERROR(INDEX('Glider Types'!$H:$H,MATCH(D26,'Glider Types'!$A:$A,0)),"") -> 185 | M26: =IFERROR(INDEX('Glider Types'!$I:$I,MATCH(D26,'Glider Types'!$A:$A,0)),"") -> 85
A27: NESA | B27: New England Soaring Association | C27: Schweizer 1-34 | D27: 1-34 | E27: N7660 | F27: 1 | G27: $10/flight | H27: Members | J27: =IFERROR(INDEX('Glider Types'!$F:$F,MATCH(D27,'Glider Types'!$A:$A,0)),"") -> 34 | K27: =IFERROR(INDEX('Glider Types'!$G:$G,MATCH(D27,'Glider Types'!$A:$A,0)),"") -> 46 | L27: =IFERROR(INDEX('Glider Types'!$H:$H,MATCH(D27,'Glider Types'!$A:$A,0)),"") -> 132 | M27: =IFERROR(INDEX('Glider Types'!$I:$I,MATCH(D27,'Glider Types'!$A:$A,0)),"") -> 114
A28: NESA | B28: New England Soaring Association | C28: Schweizer 1-26E | D28: 1-26 | E28: N65948 | F28: 1 | G28: $10/flight | H28: Members | I28: Small | J28: =IFERROR(INDEX('Glider Types'!$F:$F,MATCH(D28,'Glider Types'!$A:$A,0)),"") -> 23 | K28: =IFERROR(INDEX('Glider Types'!$G:$G,MATCH(D28,'Glider Types'!$A:$A,0)),"") -> 46 | L28: =IFERROR(INDEX('Glider Types'!$H:$H,MATCH(D28,'Glider Types'!$A:$A,0)),"") -> 161 | M28: =IFERROR(INDEX('Glider Types'!$I:$I,MATCH(D28,'Glider Types'!$A:$A,0)),"") -> 99
A29: FRANCONIA | B29: Franconia Soaring Association | C29: Grob G103 Twin Astir | D29: G103 | E29: N103GV | F29: 2 | H29: Members? | I29: Large cockpit; best bet | J29: =IFERROR(INDEX('Glider Types'!$F:$F,MATCH(D29,'Glider Types'!$A:$A,0)),"") -> 36.5 | K29: =IFERROR(INDEX('Glider Types'!$G:$G,MATCH(D29,'Glider Types'!$A:$A,0)),"") -> 57 | L29: =IFERROR(INDEX('Glider Types'!$H:$H,MATCH(D29,'Glider Types'!$A:$A,0)),"") -> 122 | M29: =IFERROR(INDEX('Glider Types'!$I:$I,MATCH(D29,'Glider Types'!$A:$A,0)),"") -> 135
A30: FRANCONIA | B30: Franconia Soaring Association | C30: LET L-23 Super Blanik | D30: L-23 | E30: N118BB | F30: 2 | H30: Members? | I30: Roomy | J30: =IFERROR(INDEX('Glider Types'!$F:$F,MATCH(D30,'Glider Types'!$A:$A,0)),"") -> 28 | K30: =IFERROR(INDEX('Glider Types'!$G:$G,MATCH(D30,'Glider Types'!$A:$A,0)),"") -> 49 | L30: =IFERROR(INDEX('Glider Types'!$H:$H,MATCH(D30,'Glider Types'!$A:$A,0)),"") -> 148 | M30: =IFERROR(INDEX('Glider Types'!$I:$I,MATCH(D30,'Glider Types'!$A:$A,0)),"") -> 135
A31: FRANCONIA | B31: Franconia Soaring Association | C31: Schweizer 2-33A | D31: 2-33 | E31: N33968 | F31: 2 | H31: Members? | I31: Roomy | J31: =IFERROR(INDEX('Glider Types'!$F:$F,MATCH(D31,'Glider Types'!$A:$A,0)),"") -> 23 | K31: =IFERROR(INDEX('Glider Types'!$G:$G,MATCH(D31,'Glider Types'!$A:$A,0)),"") -> 39 | L31: =IFERROR(INDEX('Glider Types'!$H:$H,MATCH(D31,'Glider Types'!$A:$A,0)),"") -> 185 | M31: =IFERROR(INDEX('Glider Types'!$I:$I,MATCH(D31,'Glider Types'!$A:$A,0)),"") -> 85
A32: FRANCONIA | B32: Franconia Soaring Association | C32: Schweizer 2-33A | D32: 2-33 | E32: N7776S | F32: 2 | H32: Members? | I32: Roomy | J32: =IFERROR(INDEX('Glider Types'!$F:$F,MATCH(D32,'Glider Types'!$A:$A,0)),"") -> 23 | K32: =IFERROR(INDEX('Glider Types'!$G:$G,MATCH(D32,'Glider Types'!$A:$A,0)),"") -> 39 | L32: =IFERROR(INDEX('Glider Types'!$H:$H,MATCH(D32,'Glider Types'!$A:$A,0)),"") -> 185 | M32: =IFERROR(INDEX('Glider Types'!$I:$I,MATCH(D32,'Glider Types'!$A:$A,0)),"") -> 85
A33: FRANCONIA | B33: Franconia Soaring Association | C33: Schweizer 1-26 | D33: 1-26 | E33: N2775Z | F33: 1 | H33: Members? | I33: Small | J33: =IFERROR(INDEX('Glider Types'!$F:$F,MATCH(D33,'Glider Types'!$A:$A,0)),"") -> 23 | K33: =IFERROR(INDEX('Glider Types'!$G:$G,MATCH(D33,'Glider Types'!$A:$A,0)),"") -> 46 | L33: =IFERROR(INDEX('Glider Types'!$H:$H,MATCH(D33,'Glider Types'!$A:$A,0)),"") -> 161 | M33: =IFERROR(INDEX('Glider Types'!$I:$I,MATCH(D33,'Glider Types'!$A:$A,0)),"") -> 99
A34: FRANCONIA | B34: Franconia Soaring Association | C34: Schweizer 1-26E | D34: 1-26 | E34: N606GF | F34: 1 | H34: Members? | I34: Small | J34: =IFERROR(INDEX('Glider Types'!$F:$F,MATCH(D34,'Glider Types'!$A:$A,0)),"") -> 23 | K34: =IFERROR(INDEX('Glider Types'!$G:$G,MATCH(D34,'Glider Types'!$A:$A,0)),"") -> 46 | L34: =IFERROR(INDEX('Glider Types'!$H:$H,MATCH(D34,'Glider Types'!$A:$A,0)),"") -> 161 | M34: =IFERROR(INDEX('Glider Types'!$I:$I,MATCH(D34,'Glider Types'!$A:$A,0)),"") -> 99
A35: FRANCONIA | B35: Franconia Soaring Association | C35: Pilatus B4 | D35: B4 | E35: N76PS | F35: 1 | H35: Members? | I35: Smallish | J35: =IFERROR(INDEX('Glider Types'!$F:$F,MATCH(D35,'Glider Types'!$A:$A,0)),"") -> 35 | K35: =IFERROR(INDEX('Glider Types'!$G:$G,MATCH(D35,'Glider Types'!$A:$A,0)),"") -> 46 | L35: =IFERROR(INDEX('Glider Types'!$H:$H,MATCH(D35,'Glider Types'!$A:$A,0)),"") -> 126 | M35: =IFERROR(INDEX('Glider Types'!$I:$I,MATCH(D35,'Glider Types'!$A:$A,0)),"") -> 130
A36: CSA | B36: Connecticut Soaring Association | C36: Schweizer 2-33A | D36: 2-33 | E36: N2930H | F36: 2 | H36: Members | J36: =IFERROR(INDEX('Glider Types'!$F:$F,MATCH(D36,'Glider Types'!$A:$A,0)),"") -> 23 | K36: =IFERROR(INDEX('Glider Types'!$G:$G,MATCH(D36,'Glider Types'!$A:$A,0)),"") -> 39 | L36: =IFERROR(INDEX('Glider Types'!$H:$H,MATCH(D36,'Glider Types'!$A:$A,0)),"") -> 185 | M36: =IFERROR(INDEX('Glider Types'!$I:$I,MATCH(D36,'Glider Types'!$A:$A,0)),"") -> 85
A37: CSA | B37: Connecticut Soaring Association | C37: Schweizer 2-33A | D37: 2-33 | E37: N1228S | F37: 2 | H37: Members | J37: =IFERROR(INDEX('Glider Types'!$F:$F,MATCH(D37,'Glider Types'!$A:$A,0)),"") -> 23 | K37: =IFERROR(INDEX('Glider Types'!$G:$G,MATCH(D37,'Glider Types'!$A:$A,0)),"") -> 39 | L37: =IFERROR(INDEX('Glider Types'!$H:$H,MATCH(D37,'Glider Types'!$A:$A,0)),"") -> 185 | M37: =IFERROR(INDEX('Glider Types'!$I:$I,MATCH(D37,'Glider Types'!$A:$A,0)),"") -> 85
A38: CSA | B38: Connecticut Soaring Association | C38: Schweizer 1-26E | D38: 1-26 | E38: N2517H | F38: 1 | H38: Members | I38: Small | J38: =IFERROR(INDEX('Glider Types'!$F:$F,MATCH(D38,'Glider Types'!$A:$A,0)),"") -> 23 | K38: =IFERROR(INDEX('Glider Types'!$G:$G,MATCH(D38,'Glider Types'!$A:$A,0)),"") -> 46 | L38: =IFERROR(INDEX('Glider Types'!$H:$H,MATCH(D38,'Glider Types'!$A:$A,0)),"") -> 161 | M38: =IFERROR(INDEX('Glider Types'!$I:$I,MATCH(D38,'Glider Types'!$A:$A,0)),"") -> 99
A39: CSA | B39: Connecticut Soaring Association | C39: Schweizer 1-34 | D39: 1-34 | E39: N1164S | F39: 1 | H39: Members | J39: =IFERROR(INDEX('Glider Types'!$F:$F,MATCH(D39,'Glider Types'!$A:$A,0)),"") -> 34 | K39: =IFERROR(INDEX('Glider Types'!$G:$G,MATCH(D39,'Glider Types'!$A:$A,0)),"") -> 46 | L39: =IFERROR(INDEX('Glider Types'!$H:$H,MATCH(D39,'Glider Types'!$A:$A,0)),"") -> 132 | M39: =IFERROR(INDEX('Glider Types'!$I:$I,MATCH(D39,'Glider Types'!$A:$A,0)),"") -> 114
A40: WURTS | B40: Wurtsboro Airport / Wurtsboro Flight Mgmt | C40: Grob G103A Twin II | D40: G103 | E40: not found | F40: 2 | G40: $75/h | H40: Yes | I40: Depends on proportions | J40: =IFERROR(INDEX('Glider Types'!$F:$F,MATCH(D40,'Glider Types'!$A:$A,0)),"") -> 36.5 | K40: =IFERROR(INDEX('Glider Types'!$G:$G,MATCH(D40,'Glider Types'!$A:$A,0)),"") -> 57 | L40: =IFERROR(INDEX('Glider Types'!$H:$H,MATCH(D40,'Glider Types'!$A:$A,0)),"") -> 122 | M40: =IFERROR(INDEX('Glider Types'!$I:$I,MATCH(D40,'Glider Types'!$A:$A,0)),"") -> 135
A41: WURTS | B41: Wurtsboro Airport / Wurtsboro Flight Mgmt | C41: Schweizer 2-33A | D41: 2-33 | E41: N2656H | F41: 2 | G41: $67/h | H41: Yes | I41: Roomy | J41: =IFERROR(INDEX('Glider Types'!$F:$F,MATCH(D41,'Glider Types'!$A:$A,0)),"") -> 23 | K41: =IFERROR(INDEX('Glider Types'!$G:$G,MATCH(D41,'Glider Types'!$A:$A,0)),"") -> 39 | L41: =IFERROR(INDEX('Glider Types'!$H:$H,MATCH(D41,'Glider Types'!$A:$A,0)),"") -> 185 | M41: =IFERROR(INDEX('Glider Types'!$I:$I,MATCH(D41,'Glider Types'!$A:$A,0)),"") -> 85
A42: WURTS | B42: Wurtsboro Airport / Wurtsboro Flight Mgmt | C42: Schweizer 2-33A | D42: 2-33 | E42: N65828 | F42: 2 | G42: $67/h | H42: Yes | I42: Roomy | J42: =IFERROR(INDEX('Glider Types'!$F:$F,MATCH(D42,'Glider Types'!$A:$A,0)),"") -> 23 | K42: =IFERROR(INDEX('Glider Types'!$G:$G,MATCH(D42,'Glider Types'!$A:$A,0)),"") -> 39 | L42: =IFERROR(INDEX('Glider Types'!$H:$H,MATCH(D42,'Glider Types'!$A:$A,0)),"") -> 185 | M42: =IFERROR(INDEX('Glider Types'!$I:$I,MATCH(D42,'Glider Types'!$A:$A,0)),"") -> 85
A43: WURTS | B43: Wurtsboro Airport / Wurtsboro Flight Mgmt | C43: Schweizer 1-26E | D43: 1-26 | E43: N33898 | F43: 1 | G43: $55/h | H43: Yes | I43: Little headroom | J43: =IFERROR(INDEX('Glider Types'!$F:$F,MATCH(D43,'Glider Types'!$A:$A,0)),"") -> 23 | K43: =IFERROR(INDEX('Glider Types'!$G:$G,MATCH(D43,'Glider Types'!$A:$A,0)),"") -> 46 | L43: =IFERROR(INDEX('Glider Types'!$H:$H,MATCH(D43,'Glider Types'!$A:$A,0)),"") -> 161 | M43: =IFERROR(INDEX('Glider Types'!$I:$I,MATCH(D43,'Glider Types'!$A:$A,0)),"") -> 99
A44: ACA | B44: Aero Club Albatross | C44: Grob G103 Twin Astir | D44: G103 | E44: N103GT | F44: 2 | G44: Tows only | H44: Members | I44: Depends on proportions | J44: =IFERROR(INDEX('Glider Types'!$F:$F,MATCH(D44,'Glider Types'!$A:$A,0)),"") -> 36.5 | K44: =IFERROR(INDEX('Glider Types'!$G:$G,MATCH(D44,'Glider Types'!$A:$A,0)),"") -> 57 | L44: =IFERROR(INDEX('Glider Types'!$H:$H,MATCH(D44,'Glider Types'!$A:$A,0)),"") -> 122 | M44: =IFERROR(INDEX('Glider Types'!$I:$I,MATCH(D44,'Glider Types'!$A:$A,0)),"") -> 135
A45: ACA | B45: Aero Club Albatross | C45: Rolladen-Schneider LS-4A | D45: LS-4 | E45: N3YA | F45: 1 | G45: Tows only | H45: Members | I45: Roomy | J45: =IFERROR(INDEX('Glider Types'!$F:$F,MATCH(D45,'Glider Types'!$A:$A,0)),"") -> 40.5 | K45: =IFERROR(INDEX('Glider Types'!$G:$G,MATCH(D45,'Glider Types'!$A:$A,0)),"") -> 54 | L45: =IFERROR(INDEX('Glider Types'!$H:$H,MATCH(D45,'Glider Types'!$A:$A,0)),"") -> 118 | M45: =IFERROR(INDEX('Glider Types'!$I:$I,MATCH(D45,'Glider Types'!$A:$A,0)),"") -> 146
A46: ACA | B46: Aero Club Albatross | C46: Pilatus B4 | D46: B4 | E46: N21TU | F46: 1 | G46: Tows only | H46: Members | J46: =IFERROR(INDEX('Glider Types'!$F:$F,MATCH(D46,'Glider Types'!$A:$A,0)),"") -> 35 | K46: =IFERROR(INDEX('Glider Types'!$G:$G,MATCH(D46,'Glider Types'!$A:$A,0)),"") -> 46 | L46: =IFERROR(INDEX('Glider Types'!$H:$H,MATCH(D46,'Glider Types'!$A:$A,0)),"") -> 126 | M46: =IFERROR(INDEX('Glider Types'!$I:$I,MATCH(D46,'Glider Types'!$A:$A,0)),"") -> 130
A47: ACA | B47: Aero Club Albatross | C47: Schweizer 1-34 | D47: 1-34 | E47: N134TM | F47: 1 | G47: Tows only | H47: Members | J47: =IFERROR(INDEX('Glider Types'!$F:$F,MATCH(D47,'Glider Types'!$A:$A,0)),"") -> 34 | K47: =IFERROR(INDEX('Glider Types'!$G:$G,MATCH(D47,'Glider Types'!$A:$A,0)),"") -> 46 | L47: =IFERROR(INDEX('Glider Types'!$H:$H,MATCH(D47,'Glider Types'!$A:$A,0)),"") -> 132 | M47: =IFERROR(INDEX('Glider Types'!$I:$I,MATCH(D47,'Glider Types'!$A:$A,0)),"") -> 114
A48: ACA | B48: Aero Club Albatross | C48: Schweizer 1-26 (x4) | D48: 1-26 | E48: N1118S, N17950, N2994H, N2767R | F48: 1 | G48: Tows only | H48: Members | I48: Little headroom | J48: =IFERROR(INDEX('Glider Types'!$F:$F,MATCH(D48,'Glider Types'!$A:$A,0)),"") -> 23 | K48: =IFERROR(INDEX('Glider Types'!$G:$G,MATCH(D48,'Glider Types'!$A:$A,0)),"") -> 46 | L48: =IFERROR(INDEX('Glider Types'!$H:$H,MATCH(D48,'Glider Types'!$A:$A,0)),"") -> 161 | M48: =IFERROR(INDEX('Glider Types'!$I:$I,MATCH(D48,'Glider Types'!$A:$A,0)),"") -> 99
A49: ACA | B49: Aero Club Albatross | C49: Schweizer 2-33A | D49: 2-33 | E49: N17867 | F49: 2 | G49: Tows only | H49: Members | I49: Roomy | J49: =IFERROR(INDEX('Glider Types'!$F:$F,MATCH(D49,'Glider Types'!$A:$A,0)),"") -> 23 | K49: =IFERROR(INDEX('Glider Types'!$G:$G,MATCH(D49,'Glider Types'!$A:$A,0)),"") -> 39 | L49: =IFERROR(INDEX('Glider Types'!$H:$H,MATCH(D49,'Glider Types'!$A:$A,0)),"") -> 185 | M49: =IFERROR(INDEX('Glider Types'!$I:$I,MATCH(D49,'Glider Types'!$A:$A,0)),"") -> 85
A50: ACA | B50: Aero Club Albatross | C50: Schweizer 2-33A | D50: 2-33 | E50: N65804 | F50: 2 | G50: Tows only | H50: Members | I50: Roomy | J50: =IFERROR(INDEX('Glider Types'!$F:$F,MATCH(D50,'Glider Types'!$A:$A,0)),"") -> 23 | K50: =IFERROR(INDEX('Glider Types'!$G:$G,MATCH(D50,'Glider Types'!$A:$A,0)),"") -> 39 | L50: =IFERROR(INDEX('Glider Types'!$H:$H,MATCH(D50,'Glider Types'!$A:$A,0)),"") -> 185 | M50: =IFERROR(INDEX('Glider Types'!$I:$I,MATCH(D50,'Glider Types'!$A:$A,0)),"") -> 85
A51: ACA | B51: Aero Club Albatross | C51: IS-28B2 Lark | D51: IS28 | E51: N350BB | F51: 2 | G51: Tows only | H51: Members | J51: =IFERROR(INDEX('Glider Types'!$F:$F,MATCH(D51,'Glider Types'!$A:$A,0)),"") -> 34 | K51: =IFERROR(INDEX('Glider Types'!$G:$G,MATCH(D51,'Glider Types'!$A:$A,0)),"") -> 49 | L51: =IFERROR(INDEX('Glider Types'!$H:$H,MATCH(D51,'Glider Types'!$A:$A,0)),"") -> 138 | M51: =IFERROR(INDEX('Glider Types'!$I:$I,MATCH(D51,'Glider Types'!$A:$A,0)),"") -> 113
A52: JRS | B52: Jersey Ridge Soaring | C52: Grob G103 Twin II | D52: G103 | E52: N18AG | F52: 2 | H52: Call | I52: Depends on proportions | J52: =IFERROR(INDEX('Glider Types'!$F:$F,MATCH(D52,'Glider Types'!$A:$A,0)),"") -> 36.5 | K52: =IFERROR(INDEX('Glider Types'!$G:$G,MATCH(D52,'Glider Types'!$A:$A,0)),"") -> 57 | L52: =IFERROR(INDEX('Glider Types'!$H:$H,MATCH(D52,'Glider Types'!$A:$A,0)),"") -> 122 | M52: =IFERROR(INDEX('Glider Types'!$I:$I,MATCH(D52,'Glider Types'!$A:$A,0)),"") -> 135
A53: JRS | B53: Jersey Ridge Soaring | C53: Schweizer 2-33A (x3) | D53: 2-33 | E53: N17879, N33983, N65976 | F53: 2 | H53: Call | I53: Roomy | J53: =IFERROR(INDEX('Glider Types'!$F:$F,MATCH(D53,'Glider Types'!$A:$A,0)),"") -> 23 | K53: =IFERROR(INDEX('Glider Types'!$G:$G,MATCH(D53,'Glider Types'!$A:$A,0)),"") -> 39 | L53: =IFERROR(INDEX('Glider Types'!$H:$H,MATCH(D53,'Glider Types'!$A:$A,0)),"") -> 185 | M53: =IFERROR(INDEX('Glider Types'!$I:$I,MATCH(D53,'Glider Types'!$A:$A,0)),"") -> 85
A54: JRS | B54: Jersey Ridge Soaring | C54: Schweizer 2-32 | D54: 2-32 | E54: N5772S | F54: 3 | H54: Call | I54: Roomy | J54: =IFERROR(INDEX('Glider Types'!$F:$F,MATCH(D54,'Glider Types'!$A:$A,0)),"") -> 34 | K54: =IFERROR(INDEX('Glider Types'!$G:$G,MATCH(D54,'Glider Types'!$A:$A,0)),"") -> 51 | L54: =IFERROR(INDEX('Glider Types'!$H:$H,MATCH(D54,'Glider Types'!$A:$A,0)),"") -> 144 | M54: =IFERROR(INDEX('Glider Types'!$I:$I,MATCH(D54,'Glider Types'!$A:$A,0)),"") -> 137
A55: JRS | B55: Jersey Ridge Soaring | C55: Schweizer 1-26E | D55: 1-26 | E55: N17933 | F55: 1 | H55: Call | I55: Little headroom | J55: =IFERROR(INDEX('Glider Types'!$F:$F,MATCH(D55,'Glider Types'!$A:$A,0)),"") -> 23 | K55: =IFERROR(INDEX('Glider Types'!$G:$G,MATCH(D55,'Glider Types'!$A:$A,0)),"") -> 46 | L55: =IFERROR(INDEX('Glider Types'!$H:$H,MATCH(D55,'Glider Types'!$A:$A,0)),"") -> 161 | M55: =IFERROR(INDEX('Glider Types'!$I:$I,MATCH(D55,'Glider Types'!$A:$A,0)),"") -> 99
A56: ASA | B56: Adirondack Soaring Association | C56: Grob G102 Astir CS | D56: G102 | E56: N5054 | F56: 1 | G56: Tows only | H56: Long-distance members | I56: Roomiest here | J56: =IFERROR(INDEX('Glider Types'!$F:$F,MATCH(D56,'Glider Types'!$A:$A,0)),"") -> 37 | K56: =IFERROR(INDEX('Glider Types'!$G:$G,MATCH(D56,'Glider Types'!$A:$A,0)),"") -> 51 | L56: =IFERROR(INDEX('Glider Types'!$H:$H,MATCH(D56,'Glider Types'!$A:$A,0)),"") -> 122 | M56: =IFERROR(INDEX('Glider Types'!$I:$I,MATCH(D56,'Glider Types'!$A:$A,0)),"") -> 135
A57: ASA | B57: Adirondack Soaring Association | C57: Grob G103 Twin II | D57: G103 | E57: N575AS | F57: 2 | G57: Tows only | H57: Long-distance members | I57: Depends on proportions | J57: =IFERROR(INDEX('Glider Types'!$F:$F,MATCH(D57,'Glider Types'!$A:$A,0)),"") -> 36.5 | K57: =IFERROR(INDEX('Glider Types'!$G:$G,MATCH(D57,'Glider Types'!$A:$A,0)),"") -> 57 | L57: =IFERROR(INDEX('Glider Types'!$H:$H,MATCH(D57,'Glider Types'!$A:$A,0)),"") -> 122 | M57: =IFERROR(INDEX('Glider Types'!$I:$I,MATCH(D57,'Glider Types'!$A:$A,0)),"") -> 135
A58: ASA | B58: Adirondack Soaring Association | C58: Grob G103 Twin II | D58: G103 | E58: N898AS | F58: 2 | G58: Tows only | H58: Long-distance members | I58: Depends on proportions | J58: =IFERROR(INDEX('Glider Types'!$F:$F,MATCH(D58,'Glider Types'!$A:$A,0)),"") -> 36.5 | K58: =IFERROR(INDEX('Glider Types'!$G:$G,MATCH(D58,'Glider Types'!$A:$A,0)),"") -> 57 | L58: =IFERROR(INDEX('Glider Types'!$H:$H,MATCH(D58,'Glider Types'!$A:$A,0)),"") -> 122 | M58: =IFERROR(INDEX('Glider Types'!$I:$I,MATCH(D58,'Glider Types'!$A:$A,0)),"") -> 135
A59: ASA | B59: Adirondack Soaring Association | C59: Grob G103C Twin III | D59: G103C | E59: N996T | F59: 2 | G59: Tows only | H59: Long-distance members | J59: =IFERROR(INDEX('Glider Types'!$F:$F,MATCH(D59,'Glider Types'!$A:$A,0)),"") -> 38 | K59: =IFERROR(INDEX('Glider Types'!$G:$G,MATCH(D59,'Glider Types'!$A:$A,0)),"") -> 57 | L59: =IFERROR(INDEX('Glider Types'!$H:$H,MATCH(D59,'Glider Types'!$A:$A,0)),"") -> 118 | M59: =IFERROR(INDEX('Glider Types'!$I:$I,MATCH(D59,'Glider Types'!$A:$A,0)),"") -> 140
A60: HHSC | B60: Harris Hill Soaring Corp | C60: Schleicher ASK-21 (x3) | D60: ASK-21 | E60: N521HH, N621HH, N91HH | F60: 2 | G60: $50/h guest | H60: Guest | I60: Does not fit you | J60: =IFERROR(INDEX('Glider Types'!$F:$F,MATCH(D60,'Glider Types'!$A:$A,0)),"") -> 34 | K60: =IFERROR(INDEX('Glider Types'!$G:$G,MATCH(D60,'Glider Types'!$A:$A,0)),"") -> 49 | L60: =IFERROR(INDEX('Glider Types'!$H:$H,MATCH(D60,'Glider Types'!$A:$A,0)),"") -> 128 | M60: =IFERROR(INDEX('Glider Types'!$I:$I,MATCH(D60,'Glider Types'!$A:$A,0)),"") -> 151
A61: HHSC | B61: Harris Hill Soaring Corp | C61: Schempp-Hirth Duo Discus | D61: DUO | E61: N60BP | F61: 2 | G61: $50/h guest | H61: Guest | I61: Front seat reputedly roomy | J61: =IFERROR(INDEX('Glider Types'!$F:$F,MATCH(D61,'Glider Types'!$A:$A,0)),"") -> 45 | K61: =IFERROR(INDEX('Glider Types'!$G:$G,MATCH(D61,'Glider Types'!$A:$A,0)),"") -> 54 | L61: =IFERROR(INDEX('Glider Types'!$H:$H,MATCH(D61,'Glider Types'!$A:$A,0)),"") -> 108 | M61: =IFERROR(INDEX('Glider Types'!$I:$I,MATCH(D61,'Glider Types'!$A:$A,0)),"") -> 135
A62: HHSC | B62: Harris Hill Soaring Corp | C62: Schempp-Hirth Discus CS | D62: DISCUS | E62: N189HH | F62: 1 | G62: $50/h guest | H62: Guest | J62: =IFERROR(INDEX('Glider Types'!$F:$F,MATCH(D62,'Glider Types'!$A:$A,0)),"") -> 42 | K62: =IFERROR(INDEX('Glider Types'!$G:$G,MATCH(D62,'Glider Types'!$A:$A,0)),"") -> 54 | L62: =IFERROR(INDEX('Glider Types'!$H:$H,MATCH(D62,'Glider Types'!$A:$A,0)),"") -> 116 | M62: =IFERROR(INDEX('Glider Types'!$I:$I,MATCH(D62,'Glider Types'!$A:$A,0)),"") -> 135
A63: HHSC | B63: Harris Hill Soaring Corp | C63: Schweizer 1-34 | D63: 1-34 | E63: N7654 | F63: 1 | H63: Guest | J63: =IFERROR(INDEX('Glider Types'!$F:$F,MATCH(D63,'Glider Types'!$A:$A,0)),"") -> 34 | K63: =IFERROR(INDEX('Glider Types'!$G:$G,MATCH(D63,'Glider Types'!$A:$A,0)),"") -> 46 | L63: =IFERROR(INDEX('Glider Types'!$H:$H,MATCH(D63,'Glider Types'!$A:$A,0)),"") -> 132 | M63: =IFERROR(INDEX('Glider Types'!$I:$I,MATCH(D63,'Glider Types'!$A:$A,0)),"") -> 114
A64: HHSC | B64: Harris Hill Soaring Corp | C64: Schweizer 1-35C | D64: 1-35 | E64: N3620E | F64: 1 | H64: Guest | J64: =IFERROR(INDEX('Glider Types'!$F:$F,MATCH(D64,'Glider Types'!$A:$A,0)),"") -> 38 | K64: =IFERROR(INDEX('Glider Types'!$G:$G,MATCH(D64,'Glider Types'!$A:$A,0)),"") -> 52 | L64: =IFERROR(INDEX('Glider Types'!$H:$H,MATCH(D64,'Glider Types'!$A:$A,0)),"") -> 120 | M64: =IFERROR(INDEX('Glider Types'!$I:$I,MATCH(D64,'Glider Types'!$A:$A,0)),"") -> 130
A65: HHSC | B65: Harris Hill Soaring Corp | C65: Schweizer 1-26E (x2) | D65: 1-26 | E65: N2768H, N33874 | F65: 1 | H65: Guest | I65: Little headroom | J65: =IFERROR(INDEX('Glider Types'!$F:$F,MATCH(D65,'Glider Types'!$A:$A,0)),"") -> 23 | K65: =IFERROR(INDEX('Glider Types'!$G:$G,MATCH(D65,'Glider Types'!$A:$A,0)),"") -> 46 | L65: =IFERROR(INDEX('Glider Types'!$H:$H,MATCH(D65,'Glider Types'!$A:$A,0)),"") -> 161 | M65: =IFERROR(INDEX('Glider Types'!$I:$I,MATCH(D65,'Glider Types'!$A:$A,0)),"") -> 99
A66: HHSC | B66: Harris Hill Soaring Corp | C66: Schweizer 2-33A (x3) | D66: 2-33 | E66: N17903, N65833, N65839 | F66: 2 | G66: $50/h guest | H66: Guest | I66: Roomy | J66: =IFERROR(INDEX('Glider Types'!$F:$F,MATCH(D66,'Glider Types'!$A:$A,0)),"") -> 23 | K66: =IFERROR(INDEX('Glider Types'!$G:$G,MATCH(D66,'Glider Types'!$A:$A,0)),"") -> 39 | L66: =IFERROR(INDEX('Glider Types'!$H:$H,MATCH(D66,'Glider Types'!$A:$A,0)),"") -> 185 | M66: =IFERROR(INDEX('Glider Types'!$I:$I,MATCH(D66,'Glider Types'!$A:$A,0)),"") -> 85
A67: FLSC | B67: Finger Lakes Soaring Club | C67: Schleicher ASK-21 | D67: ASK-21 | E67: N574KS | F67: 2 | H67: Members | J67: =IFERROR(INDEX('Glider Types'!$F:$F,MATCH(D67,'Glider Types'!$A:$A,0)),"") -> 34 | K67: =IFERROR(INDEX('Glider Types'!$G:$G,MATCH(D67,'Glider Types'!$A:$A,0)),"") -> 49 | L67: =IFERROR(INDEX('Glider Types'!$H:$H,MATCH(D67,'Glider Types'!$A:$A,0)),"") -> 128 | M67: =IFERROR(INDEX('Glider Types'!$I:$I,MATCH(D67,'Glider Types'!$A:$A,0)),"") -> 151
A68: FLSC | B68: Finger Lakes Soaring Club | C68: Grob G102 Astir CS | D68: G102 | E68: N20737 | F68: 1 | H68: Members | I68: Roomy | J68: =IFERROR(INDEX('Glider Types'!$F:$F,MATCH(D68,'Glider Types'!$A:$A,0)),"") -> 37 | K68: =IFERROR(INDEX('Glider Types'!$G:$G,MATCH(D68,'Glider Types'!$A:$A,0)),"") -> 51 | L68: =IFERROR(INDEX('Glider Types'!$H:$H,MATCH(D68,'Glider Types'!$A:$A,0)),"") -> 122 | M68: =IFERROR(INDEX('Glider Types'!$I:$I,MATCH(D68,'Glider Types'!$A:$A,0)),"") -> 135
A69: FLSC | B69: Finger Lakes Soaring Club | C69: Centrair Pegasus 101B | D69: PEGASUS | E69: N70FP | F69: 1 | H69: Members | J69: =IFERROR(INDEX('Glider Types'!$F:$F,MATCH(D69,'Glider Types'!$A:$A,0)),"") -> 41 | K69: =IFERROR(INDEX('Glider Types'!$G:$G,MATCH(D69,'Glider Types'!$A:$A,0)),"") -> 54 | L69: =IFERROR(INDEX('Glider Types'!$H:$H,MATCH(D69,'Glider Types'!$A:$A,0)),"") -> 118 | M69: =IFERROR(INDEX('Glider Types'!$I:$I,MATCH(D69,'Glider Types'!$A:$A,0)),"") -> 135
A70: FLSC | B70: Finger Lakes Soaring Club | C70: Schweizer 1-26A | D70: 1-26 | E70: N3822A | F70: 1 | H70: Members | I70: 15 flights in type required | J70: =IFERROR(INDEX('Glider Types'!$F:$F,MATCH(D70,'Glider Types'!$A:$A,0)),"") -> 23 | K70: =IFERROR(INDEX('Glider Types'!$G:$G,MATCH(D70,'Glider Types'!$A:$A,0)),"") -> 46 | L70: =IFERROR(INDEX('Glider Types'!$H:$H,MATCH(D70,'Glider Types'!$A:$A,0)),"") -> 161 | M70: =IFERROR(INDEX('Glider Types'!$I:$I,MATCH(D70,'Glider Types'!$A:$A,0)),"") -> 99
A71: FLSC | B71: Finger Lakes Soaring Club | C71: Schweizer 2-33A | D71: 2-33 | E71: N234WE | F71: 2 | H71: Members | I71: Roomy | J71: =IFERROR(INDEX('Glider Types'!$F:$F,MATCH(D71,'Glider Types'!$A:$A,0)),"") -> 23 | K71: =IFERROR(INDEX('Glider Types'!$G:$G,MATCH(D71,'Glider Types'!$A:$A,0)),"") -> 39 | L71: =IFERROR(INDEX('Glider Types'!$H:$H,MATCH(D71,'Glider Types'!$A:$A,0)),"") -> 185 | M71: =IFERROR(INDEX('Glider Types'!$I:$I,MATCH(D71,'Glider Types'!$A:$A,0)),"") -> 85
A72: VSC | B72: Valley Soaring Club | C72: Schleicher ASK-21 | D72: ASK-21 | E72: N474KS | F72: 2 | H72: Members | J72: =IFERROR(INDEX('Glider Types'!$F:$F,MATCH(D72,'Glider Types'!$A:$A,0)),"") -> 34 | K72: =IFERROR(INDEX('Glider Types'!$G:$G,MATCH(D72,'Glider Types'!$A:$A,0)),"") -> 49 | L72: =IFERROR(INDEX('Glider Types'!$H:$H,MATCH(D72,'Glider Types'!$A:$A,0)),"") -> 128 | M72: =IFERROR(INDEX('Glider Types'!$I:$I,MATCH(D72,'Glider Types'!$A:$A,0)),"") -> 151
A73: VSC | B73: Valley Soaring Club | C73: Schweizer 2-33 (x3) | D73: 2-33 | E73: N2463W, N5787S, N7686 | F73: 2 | H73: Members | I73: Roomy | J73: =IFERROR(INDEX('Glider Types'!$F:$F,MATCH(D73,'Glider Types'!$A:$A,0)),"") -> 23 | K73: =IFERROR(INDEX('Glider Types'!$G:$G,MATCH(D73,'Glider Types'!$A:$A,0)),"") -> 39 | L73: =IFERROR(INDEX('Glider Types'!$H:$H,MATCH(D73,'Glider Types'!$A:$A,0)),"") -> 185 | M73: =IFERROR(INDEX('Glider Types'!$I:$I,MATCH(D73,'Glider Types'!$A:$A,0)),"") -> 85
A74: VSC | B74: Valley Soaring Club | C74: Schweizer 1-34 | D74: 1-34 | E74: N1172S | F74: 1 | H74: Members | J74: =IFERROR(INDEX('Glider Types'!$F:$F,MATCH(D74,'Glider Types'!$A:$A,0)),"") -> 34 | K74: =IFERROR(INDEX('Glider Types'!$G:$G,MATCH(D74,'Glider Types'!$A:$A,0)),"") -> 46 | L74: =IFERROR(INDEX('Glider Types'!$H:$H,MATCH(D74,'Glider Types'!$A:$A,0)),"") -> 132 | M74: =IFERROR(INDEX('Glider Types'!$I:$I,MATCH(D74,'Glider Types'!$A:$A,0)),"") -> 114
A75: VSC | B75: Valley Soaring Club | C75: Schweizer 1-26E | D75: 1-26 | E75: N17924 | F75: 1 | H75: Members | J75: =IFERROR(INDEX('Glider Types'!$F:$F,MATCH(D75,'Glider Types'!$A:$A,0)),"") -> 23 | K75: =IFERROR(INDEX('Glider Types'!$G:$G,MATCH(D75,'Glider Types'!$A:$A,0)),"") -> 46 | L75: =IFERROR(INDEX('Glider Types'!$H:$H,MATCH(D75,'Glider Types'!$A:$A,0)),"") -> 161 | M75: =IFERROR(INDEX('Glider Types'!$I:$I,MATCH(D75,'Glider Types'!$A:$A,0)),"") -> 99
A76: LISA | B76: Long Island Soaring Association | C76: Schweizer 2-33A (x3) | D76: 2-33 | E76: N17956, N2055T, N65918 | F76: 2 | H76: Members | I76: Roomy | J76: =IFERROR(INDEX('Glider Types'!$F:$F,MATCH(D76,'Glider Types'!$A:$A,0)),"") -> 23 | K76: =IFERROR(INDEX('Glider Types'!$G:$G,MATCH(D76,'Glider Types'!$A:$A,0)),"") -> 39 | L76: =IFERROR(INDEX('Glider Types'!$H:$H,MATCH(D76,'Glider Types'!$A:$A,0)),"") -> 185 | M76: =IFERROR(INDEX('Glider Types'!$I:$I,MATCH(D76,'Glider Types'!$A:$A,0)),"") -> 85
A77: LISA | B77: Long Island Soaring Association | C77: Schweizer 1-34 | D77: 1-34 | E77: N7635 | F77: 1 | H77: Members | J77: =IFERROR(INDEX('Glider Types'!$F:$F,MATCH(D77,'Glider Types'!$A:$A,0)),"") -> 34 | K77: =IFERROR(INDEX('Glider Types'!$G:$G,MATCH(D77,'Glider Types'!$A:$A,0)),"") -> 46 | L77: =IFERROR(INDEX('Glider Types'!$H:$H,MATCH(D77,'Glider Types'!$A:$A,0)),"") -> 132 | M77: =IFERROR(INDEX('Glider Types'!$I:$I,MATCH(D77,'Glider Types'!$A:$A,0)),"") -> 114
A78: LISA | B78: Long Island Soaring Association | C78: Schweizer 1-26E | D78: 1-26 | E78: N17917 | F78: 1 | H78: Members | J78: =IFERROR(INDEX('Glider Types'!$F:$F,MATCH(D78,'Glider Types'!$A:$A,0)),"") -> 23 | K78: =IFERROR(INDEX('Glider Types'!$G:$G,MATCH(D78,'Glider Types'!$A:$A,0)),"") -> 46 | L78: =IFERROR(INDEX('Glider Types'!$H:$H,MATCH(D78,'Glider Types'!$A:$A,0)),"") -> 161 | M78: =IFERROR(INDEX('Glider Types'!$I:$I,MATCH(D78,'Glider Types'!$A:$A,0)),"") -> 99
A79: VANSANT | B79: Van Sant Airport / Bird of Paradise | C79: Schweizer 2-33 | D79: 2-33 | E79: not found | F79: 2 | G79: $80/h + tow | H79: Yes | I79: Roomy | J79: =IFERROR(INDEX('Glider Types'!$F:$F,MATCH(D79,'Glider Types'!$A:$A,0)),"") -> 23 | K79: =IFERROR(INDEX('Glider Types'!$G:$G,MATCH(D79,'Glider Types'!$A:$A,0)),"") -> 39 | L79: =IFERROR(INDEX('Glider Types'!$H:$H,MATCH(D79,'Glider Types'!$A:$A,0)),"") -> 185 | M79: =IFERROR(INDEX('Glider Types'!$I:$I,MATCH(D79,'Glider Types'!$A:$A,0)),"") -> 85
A80: VANSANT | B80: Van Sant Airport / Bird of Paradise | C80: Schweizer 2-32 | D80: 2-32 | E80: not found | F80: 3 | G80: $80/h + tow | H80: Yes | I80: Roomy | J80: =IFERROR(INDEX('Glider Types'!$F:$F,MATCH(D80,'Glider Types'!$A:$A,0)),"") -> 34 | K80: =IFERROR(INDEX('Glider Types'!$G:$G,MATCH(D80,'Glider Types'!$A:$A,0)),"") -> 51 | L80: =IFERROR(INDEX('Glider Types'!$H:$H,MATCH(D80,'Glider Types'!$A:$A,0)),"") -> 144 | M80: =IFERROR(INDEX('Glider Types'!$I:$I,MATCH(D80,'Glider Types'!$A:$A,0)),"") -> 137
A81: TIGERS | B81: Soaring Tigers | C81: Schweizer 2-33A | D81: 2-33 | E81: N65867 | F81: 2 | G81: Tows only | H81: Members | J81: =IFERROR(INDEX('Glider Types'!$F:$F,MATCH(D81,'Glider Types'!$A:$A,0)),"") -> 23 | K81: =IFERROR(INDEX('Glider Types'!$G:$G,MATCH(D81,'Glider Types'!$A:$A,0)),"") -> 39 | L81: =IFERROR(INDEX('Glider Types'!$H:$H,MATCH(D81,'Glider Types'!$A:$A,0)),"") -> 185 | M81: =IFERROR(INDEX('Glider Types'!$I:$I,MATCH(D81,'Glider Types'!$A:$A,0)),"") -> 85
A82: TIGERS | B82: Soaring Tigers | C82: Schweizer 1-26B | D82: 1-26 | E82: N389BR | F82: 1 | G82: Tows only | H82: Members | J82: =IFERROR(INDEX('Glider Types'!$F:$F,MATCH(D82,'Glider Types'!$A:$A,0)),"") -> 23 | K82: =IFERROR(INDEX('Glider Types'!$G:$G,MATCH(D82,'Glider Types'!$A:$A,0)),"") -> 46 | L82: =IFERROR(INDEX('Glider Types'!$H:$H,MATCH(D82,'Glider Types'!$A:$A,0)),"") -> 161 | M82: =IFERROR(INDEX('Glider Types'!$I:$I,MATCH(D82,'Glider Types'!$A:$A,0)),"") -> 99
A83: TIGERS | B83: Soaring Tigers | C83: Schweizer 1-34 | D83: 1-34 | E83: N76JP | F83: 1 | G83: Tows only | H83: Members | J83: =IFERROR(INDEX('Glider Types'!$F:$F,MATCH(D83,'Glider Types'!$A:$A,0)),"") -> 34 | K83: =IFERROR(INDEX('Glider Types'!$G:$G,MATCH(D83,'Glider Types'!$A:$A,0)),"") -> 46 | L83: =IFERROR(INDEX('Glider Types'!$H:$H,MATCH(D83,'Glider Types'!$A:$A,0)),"") -> 132 | M83: =IFERROR(INDEX('Glider Types'!$I:$I,MATCH(D83,'Glider Types'!$A:$A,0)),"") -> 114
A84: PGC | B84: Philadelphia Glider Council | C84: Grob G103 family (x5) | D84: G103 | E84: N139BG, N5QD, N924BG, N487GC, N5361V | F84: 2 | G84: Tows only | H84: Members | I84: Depends on proportions | J84: =IFERROR(INDEX('Glider Types'!$F:$F,MATCH(D84,'Glider Types'!$A:$A,0)),"") -> 36.5 | K84: =IFERROR(INDEX('Glider Types'!$G:$G,MATCH(D84,'Glider Types'!$A:$A,0)),"") -> 57 | L84: =IFERROR(INDEX('Glider Types'!$H:$H,MATCH(D84,'Glider Types'!$A:$A,0)),"") -> 122 | M84: =IFERROR(INDEX('Glider Types'!$I:$I,MATCH(D84,'Glider Types'!$A:$A,0)),"") -> 135
A85: PGC | B85: Philadelphia Glider Council | C85: Grob G102 / Astir CS-77 | D85: G102 | E85: N131SS, N1006P | F85: 1 | G85: Tows only | H85: Members | I85: Roomy | J85: =IFERROR(INDEX('Glider Types'!$F:$F,MATCH(D85,'Glider Types'!$A:$A,0)),"") -> 37 | K85: =IFERROR(INDEX('Glider Types'!$G:$G,MATCH(D85,'Glider Types'!$A:$A,0)),"") -> 51 | L85: =IFERROR(INDEX('Glider Types'!$H:$H,MATCH(D85,'Glider Types'!$A:$A,0)),"") -> 122 | M85: =IFERROR(INDEX('Glider Types'!$I:$I,MATCH(D85,'Glider Types'!$A:$A,0)),"") -> 135
A86: PGC | B86: Philadelphia Glider Council | C86: Schempp-Hirth Duo Discus | D86: DUO | E86: N90BP | F86: 2 | G86: Tows only | H86: Members | J86: =IFERROR(INDEX('Glider Types'!$F:$F,MATCH(D86,'Glider Types'!$A:$A,0)),"") -> 45 | K86: =IFERROR(INDEX('Glider Types'!$G:$G,MATCH(D86,'Glider Types'!$A:$A,0)),"") -> 54 | L86: =IFERROR(INDEX('Glider Types'!$H:$H,MATCH(D86,'Glider Types'!$A:$A,0)),"") -> 108 | M86: =IFERROR(INDEX('Glider Types'!$I:$I,MATCH(D86,'Glider Types'!$A:$A,0)),"") -> 135
A87: PGC | B87: Philadelphia Glider Council | C87: Schweizer 2-22 | D87: 2-22 | E87: N91834 | F87: 2 | G87: Tows only | H87: Members | J87: =IFERROR(INDEX('Glider Types'!$F:$F,MATCH(D87,'Glider Types'!$A:$A,0)),"") -> 17 | K87: =IFERROR(INDEX('Glider Types'!$G:$G,MATCH(D87,'Glider Types'!$A:$A,0)),"") -> 42 | L87: =IFERROR(INDEX('Glider Types'!$H:$H,MATCH(D87,'Glider Types'!$A:$A,0)),"") -> 197 | M87: =IFERROR(INDEX('Glider Types'!$I:$I,MATCH(D87,'Glider Types'!$A:$A,0)),"") -> 63
A88: BSA | B88: Brandywine Soaring Association | C88: Schleicher ASK-21 | D88: ASK-21 | E88: N214BS | F88: 2 | H88: Members | I88: Does not fit you | J88: =IFERROR(INDEX('Glider Types'!$F:$F,MATCH(D88,'Glider Types'!$A:$A,0)),"") -> 34 | K88: =IFERROR(INDEX('Glider Types'!$G:$G,MATCH(D88,'Glider Types'!$A:$A,0)),"") -> 49 | L88: =IFERROR(INDEX('Glider Types'!$H:$H,MATCH(D88,'Glider Types'!$A:$A,0)),"") -> 128 | M88: =IFERROR(INDEX('Glider Types'!$I:$I,MATCH(D88,'Glider Types'!$A:$A,0)),"") -> 151
A89: BSA | B89: Brandywine Soaring Association | C89: LET L-23 Super Blanik | D89: L-23 | E89: N316BA | F89: 2 | H89: Members | I89: Roomy | J89: =IFERROR(INDEX('Glider Types'!$F:$F,MATCH(D89,'Glider Types'!$A:$A,0)),"") -> 28 | K89: =IFERROR(INDEX('Glider Types'!$G:$G,MATCH(D89,'Glider Types'!$A:$A,0)),"") -> 49 | L89: =IFERROR(INDEX('Glider Types'!$H:$H,MATCH(D89,'Glider Types'!$A:$A,0)),"") -> 148 | M89: =IFERROR(INDEX('Glider Types'!$I:$I,MATCH(D89,'Glider Types'!$A:$A,0)),"") -> 135
A90: BSA | B90: Brandywine Soaring Association | C90: Grob G103 Twin Astir | D90: G103 | E90: N906BG | F90: 2 | H90: Members | J90: =IFERROR(INDEX('Glider Types'!$F:$F,MATCH(D90,'Glider Types'!$A:$A,0)),"") -> 36.5 | K90: =IFERROR(INDEX('Glider Types'!$G:$G,MATCH(D90,'Glider Types'!$A:$A,0)),"") -> 57 | L90: =IFERROR(INDEX('Glider Types'!$H:$H,MATCH(D90,'Glider Types'!$A:$A,0)),"") -> 122 | M90: =IFERROR(INDEX('Glider Types'!$I:$I,MATCH(D90,'Glider Types'!$A:$A,0)),"") -> 135
A91: BSA | B91: Brandywine Soaring Association | C91: Schweizer 1-26E (x2) | D91: 1-26 | E91: N1106S, N8642 | F91: 1 | H91: Members | J91: =IFERROR(INDEX('Glider Types'!$F:$F,MATCH(D91,'Glider Types'!$A:$A,0)),"") -> 23 | K91: =IFERROR(INDEX('Glider Types'!$G:$G,MATCH(D91,'Glider Types'!$A:$A,0)),"") -> 46 | L91: =IFERROR(INDEX('Glider Types'!$H:$H,MATCH(D91,'Glider Types'!$A:$A,0)),"") -> 161 | M91: =IFERROR(INDEX('Glider Types'!$I:$I,MATCH(D91,'Glider Types'!$A:$A,0)),"") -> 99
A92: PSA | B92: Pittsburgh Soaring Association | C92: Grob G103 | D92: G103 | E92: N103X | F92: 2 | G92: $10/h | H92: Temp member | I92: Depends on proportions | J92: =IFERROR(INDEX('Glider Types'!$F:$F,MATCH(D92,'Glider Types'!$A:$A,0)),"") -> 36.5 | K92: =IFERROR(INDEX('Glider Types'!$G:$G,MATCH(D92,'Glider Types'!$A:$A,0)),"") -> 57 | L92: =IFERROR(INDEX('Glider Types'!$H:$H,MATCH(D92,'Glider Types'!$A:$A,0)),"") -> 122 | M92: =IFERROR(INDEX('Glider Types'!$I:$I,MATCH(D92,'Glider Types'!$A:$A,0)),"") -> 135
A93: PSA | B93: Pittsburgh Soaring Association | C93: Grob G102 | D93: G102 | E93: N412SS / N142SS | F93: 1 | G93: $10/h | H93: Temp member (rated) | I93: Roomy | J93: =IFERROR(INDEX('Glider Types'!$F:$F,MATCH(D93,'Glider Types'!$A:$A,0)),"") -> 37 | K93: =IFERROR(INDEX('Glider Types'!$G:$G,MATCH(D93,'Glider Types'!$A:$A,0)),"") -> 51 | L93: =IFERROR(INDEX('Glider Types'!$H:$H,MATCH(D93,'Glider Types'!$A:$A,0)),"") -> 122 | M93: =IFERROR(INDEX('Glider Types'!$I:$I,MATCH(D93,'Glider Types'!$A:$A,0)),"") -> 135
A94: PSA | B94: Pittsburgh Soaring Association | C94: LET L-23 Super Blanik | D94: L-23 | E94: N916B | F94: 2 | G94: $10/h | H94: Temp member | I94: Roomy | J94: =IFERROR(INDEX('Glider Types'!$F:$F,MATCH(D94,'Glider Types'!$A:$A,0)),"") -> 28 | K94: =IFERROR(INDEX('Glider Types'!$G:$G,MATCH(D94,'Glider Types'!$A:$A,0)),"") -> 49 | L94: =IFERROR(INDEX('Glider Types'!$H:$H,MATCH(D94,'Glider Types'!$A:$A,0)),"") -> 148 | M94: =IFERROR(INDEX('Glider Types'!$I:$I,MATCH(D94,'Glider Types'!$A:$A,0)),"") -> 135
A95: MASA | B95: Mid-Atlantic Soaring Association | C95: Schleicher ASK-21 | D95: ASK-21 | E95: N899MA | F95: 2 | H95: Members | I95: Does not fit you | J95: =IFERROR(INDEX('Glider Types'!$F:$F,MATCH(D95,'Glider Types'!$A:$A,0)),"") -> 34 | K95: =IFERROR(INDEX('Glider Types'!$G:$G,MATCH(D95,'Glider Types'!$A:$A,0)),"") -> 49 | L95: =IFERROR(INDEX('Glider Types'!$H:$H,MATCH(D95,'Glider Types'!$A:$A,0)),"") -> 128 | M95: =IFERROR(INDEX('Glider Types'!$I:$I,MATCH(D95,'Glider Types'!$A:$A,0)),"") -> 151
A96: MASA | B96: Mid-Atlantic Soaring Association | C96: Schleicher ASK-21 (hand rudder) | D96: ASK-21 | E96: N899SA | F96: 2 | H96: Members | I96: Does not fit you | J96: =IFERROR(INDEX('Glider Types'!$F:$F,MATCH(D96,'Glider Types'!$A:$A,0)),"") -> 34 | K96: =IFERROR(INDEX('Glider Types'!$G:$G,MATCH(D96,'Glider Types'!$A:$A,0)),"") -> 49 | L96: =IFERROR(INDEX('Glider Types'!$H:$H,MATCH(D96,'Glider Types'!$A:$A,0)),"") -> 128 | M96: =IFERROR(INDEX('Glider Types'!$I:$I,MATCH(D96,'Glider Types'!$A:$A,0)),"") -> 151
A97: MASA | B97: Mid-Atlantic Soaring Association | C97: Schweizer 2-33A | D97: 2-33 | E97: N7782S | F97: 2 | H97: Members | I97: Roomy | J97: =IFERROR(INDEX('Glider Types'!$F:$F,MATCH(D97,'Glider Types'!$A:$A,0)),"") -> 23 | K97: =IFERROR(INDEX('Glider Types'!$G:$G,MATCH(D97,'Glider Types'!$A:$A,0)),"") -> 39 | L97: =IFERROR(INDEX('Glider Types'!$H:$H,MATCH(D97,'Glider Types'!$A:$A,0)),"") -> 185 | M97: =IFERROR(INDEX('Glider Types'!$I:$I,MATCH(D97,'Glider Types'!$A:$A,0)),"") -> 85
A98: MASA | B98: Mid-Atlantic Soaring Association | C98: Grob G102 Club Astir IIIB | D98: G102 | E98: N936BG | F98: 1 | H98: Members | J98: =IFERROR(INDEX('Glider Types'!$F:$F,MATCH(D98,'Glider Types'!$A:$A,0)),"") -> 37 | K98: =IFERROR(INDEX('Glider Types'!$G:$G,MATCH(D98,'Glider Types'!$A:$A,0)),"") -> 51 | L98: =IFERROR(INDEX('Glider Types'!$H:$H,MATCH(D98,'Glider Types'!$A:$A,0)),"") -> 122 | M98: =IFERROR(INDEX('Glider Types'!$I:$I,MATCH(D98,'Glider Types'!$A:$A,0)),"") -> 135
A99: MASA | B99: Mid-Atlantic Soaring Association | C99: Rolladen-Schneider LS-4 | D99: LS-4 | E99: N30RD | F99: 1 | H99: Members | J99: =IFERROR(INDEX('Glider Types'!$F:$F,MATCH(D99,'Glider Types'!$A:$A,0)),"") -> 40.5 | K99: =IFERROR(INDEX('Glider Types'!$G:$G,MATCH(D99,'Glider Types'!$A:$A,0)),"") -> 54 | L99: =IFERROR(INDEX('Glider Types'!$H:$H,MATCH(D99,'Glider Types'!$A:$A,0)),"") -> 118 | M99: =IFERROR(INDEX('Glider Types'!$I:$I,MATCH(D99,'Glider Types'!$A:$A,0)),"") -> 146
A100: SKYLINE | B100: Skyline Soaring Club | C100: Schleicher ASK-21 (x2) | D100: ASK-21 | E100: not found | F100: 2 | G100: $39/h | H100: Visiting member | I100: Does not fit you | J100: =IFERROR(INDEX('Glider Types'!$F:$F,MATCH(D100,'Glider Types'!$A:$A,0)),"") -> 34 | K100: =IFERROR(INDEX('Glider Types'!$G:$G,MATCH(D100,'Glider Types'!$A:$A,0)),"") -> 49 | L100: =IFERROR(INDEX('Glider Types'!$H:$H,MATCH(D100,'Glider Types'!$A:$A,0)),"") -> 128 | M100: =IFERROR(INDEX('Glider Types'!$I:$I,MATCH(D100,'Glider Types'!$A:$A,0)),"") -> 151
...

Sheet Travel
A1: Tier | B1: Destination | C1: Carriers (nonstop from BOS) | D1: Friday evening timing | E1: Round-trip fare (KAYAK typical) | F1: Nearest soaring
A2: A | B2: ORD / MDW | C2: AA, UA / WN | D2: ~8-9 pm dep, arr ~10-11 pm CT | E2: $181-308 typ | F2: Sky Soaring ~0:50; Chicago Glider Club ~1:00
A3: A | B3: PHL | C3: AA, DL, B6 | D3: 9:29 pm -> 11:09 pm | E3: $191-347 typ | F3: Van Sant ~1:15; Blairstown ~1:45
A4: A | B4: DCA | C4: AA, DL, B6 | D4: earlier than 10:48 pm | E4: $185-332 typ | F4: Fairfield PA ~1:30; Skyline
A5: A | B5: BWI | C5: WN, DL | D5: 10:20 pm -> ~12:00 am | E5: $213-364; last-minute +103% | F5: Fairfield PA ~1:20
A6: A | B6: ATL | C6: DL, B6, F9 | D6: ~8 pm dep | E6: $196-360 typ | F6: Chilhowee ~2:15; MGSA ~1:00
A7: A | B7: MCO | C7: B6, DL, F9 | D7: 7-8 pm dep | E7: $209-395 typ | F7: Seminole-Lake ~0:45
A8: A | B8: SYR / BUF | C8: AA, B6, DL | D8: ~8:30-9:50 pm | E8: $197-338 typ | F8: Harris Hill 1:45-2:30
A9: A | B9: RDU | C9: DL, B6, F9 | D9: 9:45 pm -> 11:56 pm | E9: $182-346 typ | F9: NCSA ~0:45
A10: B | B10: DEN | C10: UA, WN, B6, DL | D10: 9:06 pm -> 11:48 pm MT | E10: $278-468; avg $365 | F10: Boulder ~0:45
A11: B | B11: CLT | C11: AA, DL | D11: 8:10 pm -> 10:44 pm | E11: $296-429 | F11: Bermuda High ~1:15
A12: B | B12: IAD | C12: UA | D12: 7:41 pm (tight) | E12: $226-377 | F12: Skyline, Eastern Soaring
... A22: C | B22: RNO | C22: none nonstop | D22: n/a | E22: n/a | F22: Minden: not reachable Friday night
A24: Tier A: plausibly under $300 booked 2-3 days out. Tier B: sometimes, watch for sales. Tier C: rarely.
A25: Fares from KAYAK route pages, Sept 2026; booking within 2 weeks runs 10-100% above average. Spirit ceased operations 2 May 2026.
A26: Earliest realistic BOS departure leaving Newton at 5:30 pm Friday: about 7:00-7:15 pm.

Sheet Contact Log
A1: Date | B1: Operator ID | C1: Operator | D1: Person | E1: Method | F1: What I asked | G1: Outcome | H1: Next step | I1: Status
A2: 2026-09-22 (example) | B2: SUGAR | C2: =IFERROR(INDEX(Operators!$B:$B,MATCH(B2,Operators!$A:$A,0)),"") -> Sugarbush Soaring | D2: Front desk | E2: Phone | F2: Rental checkout rules for licensed visitor; which ship fits a tall pilot | G2: (example row) | H2: Book checkout day | I2: Not started
C3: =IFERROR(INDEX(Operators!$B:$B,MATCH(B3,Operators!$A:$A,0)),"")
C4: =IFERROR(INDEX(Operators!$B:$B,MATCH(B4,Operators!$A:$A,0)),"")
C5: =IFERROR(INDEX(Operators!$B:$B,MATCH(B5,Operators!$A:$A,0)),"")
C6: =IFERROR(INDEX(Operators!$B:$B,MATCH(B6,Operators!$A:$A,0)),"")
C7: =IFERROR(INDEX(Operators!$B:$B,MATCH(B7,Operators!$A:$A,0)),"")
C8: =IFERROR(INDEX(Operators!$B:$B,MATCH(B8,Operators!$A:$A,0)),"")
C9: =IFERROR(INDEX(Operators!$B:$B,MATCH(B9,Operators!$A:$A,0)),"")
C10: =IFERROR(INDEX(Operators!$B:$B,MATCH(B10,Operators!$A:$A,0)),"")
C11: =IFERROR(INDEX(Operators!$B:$B,MATCH(B11,Operators!$A:$A,0)),"")
C12: =IFERROR(INDEX(Operators!$B:$B,MATCH(B12,Operators!$A:$A,0)),"")
C13: =IFERROR(INDEX(Operators!$B:$B,MATCH(B13,Operators!$A:$A,0)),"")
C14: =IFERROR(INDEX(Operators!$B:$B,MATCH(B14,Operators!$A:$A,0)),"")
... C59: =IFERROR(INDEX(Operators!$B:$B,MATCH(B59,Operators!$A:$A,0)),"")
